Workbook

Sheet DASHBOARD
A1: GODREJ PROPERTIES
A2: REAL ESTATE SALES AUTOMATION SYSTEM | ASM COMMAND CENTER | FY 2024-25
A3: Live Dashboard · 22 June 2026 · Area Sales Manager View · All Figures in ₹
A5: KEY PERFORMANCE INDICATORS
A6: 📋 TOTAL LEADS | E6: 🏗️ SITE VISITS | I6: ✅ BOOKINGS | M6: 💰 REVENUE | Q6: 🎯 CONVERSION | U6: ⚠️ OUTSTANDING
A8: 500 | E8: 281 | I8: 85 | M8: ₹122.7 Cr | Q8: 17.0% | U8: ₹48.9 Cr
A10: All Sources · FY 2024-25 | E10: Completed & Scheduled | I10: Confirmed Transactions | M10: Total Property Sales Value | Q10: Lead to Booking Ratio | U10: Pending Collections
A12: PERFORMANCE METRICS
A13: Avg Deal Size | E13: Active Pipeline | I13: Lost Leads | M13: Overdue Follow-ups | Q13: Site Visit Ratio | U13: Booking Rate
A14: ₹144L | E14: 368 Leads | I14: 47 | M14: 128 | Q14: 56.2% | U14: 30.2%
A18: 📈 MONTHLY REVENUE & BOOKING TREND | N18: 🎯 SALES FUNNEL ANALYSIS
A40: 🌐 LEAD SOURCE BREAKDOWN | N40: 🏗️ PROJECT-WISE REVENUE
A59: 🏆 EXECUTIVE PERFORMANCE RANKING | N59: 📅 MONTHLY BOOKING TREND
A77: GODREJ PROPERTIES — REAL ESTATE SALES AUTOMATION SYSTEM | CONFIDENTIAL — FOR INTERNAL USE ONLY Area Sales Manager Dashboard | All Figures in Indian Rupees (₹) | FY 2024-25 Generated: 22 June 2026 | Designed by: CRM & Sales Operations Team
A81: 🎯 TARGET vs ACHIEVEMENT TRACKER | FY 2024-25
A82: Monthly targets vs actuals | Color coded: Green = On/Above Target | Red = Below Target
A83: Month | B83: Lead Target | C83: Leads Actual | D83: Lead Ach% | E83: Booking Target | F83: Bookings Actual | G83: Booking Ach% | H83: Rev Target (₹Cr) | I83: Rev Actual (₹Cr) | J83: Rev Ach%
A84: Apr 24 | B84: 45 | C84: 34 | D84: =IFERROR(C84/B84,0) -> 0.75555556 | E84: 7 | F84: 6 | G84: =IFERROR(F84/E84,0) -> 0.85714286 | H84: 15 | I84: 4.92 | J84: =IFERROR(I84/H84,0) -> 0.328
A85: May 24 | B85: 48 | C85: 47 | D85: =IFERROR(C85/B85,0) -> 0.97916667 | E85: 8 | F85: 9 | G85: =IFERROR(F85/E85,0) -> 1.125 | H85: 16 | I85: 7.67 | J85: =IFERROR(I85/H85,0) -> 0.479375
A86: Jun 24 | B86: 48 | C86: 46 | D86: =IFERROR(C86/B86,0) -> 0.95833333 | E86: 8 | F86: 8 | G86: =IFERROR(F86/E86,0) -> 1 | H86: 16 | I86: 12.3 | J86: =IFERROR(I86/H86,0) -> 0.76875
A87: Jul 24 | B87: 45 | C87: 39 | D87: =IFERROR(C87/B87,0) -> 0.86666667 | E87: 8 | F87: 9 | G87: =IFERROR(F87/E87,0) -> 1.125 | H87: 16 | I87: 8.12 | J87: =IFERROR(I87/H87,0) -> 0.5075
A88: Aug 24 | B88: 45 | C88: 39 | D88: =IFERROR(C88/B88,0) -> 0.86666667 | E88: 8 | F88: 8 | G88: =IFERROR(F88/E88,0) -> 1 | H88: 16 | I88: 17.75 | J88: =IFERROR(I88/H88,0) -> 1.109375
A89: Sep 24 | B89: 45 | C89: 40 | D89: =IFERROR(C89/B89,0) -> 0.88888889 | E89: 7 | F89: 3 | G89: =IFERROR(F89/E89,0) -> 0.42857143 | H89: 14 | I89: 10.34 | J89: =IFERROR(I89/H89,0) -> 0.73857143
A90: Oct 24 | B90: 50 | C90: 48 | D90: =IFERROR(C90/B90,0) -> 0.96 | E90: 8 | F90: 7 | G90: =IFERROR(F90/E90,0) -> 0.875 | H90: 16 | I90: 3.38 | J90: =IFERROR(I90/H90,0) -> 0.21125
A91: Nov 24 | B91: 50 | C91: 52 | D91: =IFERROR(C91/B91,0) -> 1.04 | E91: 9 | F91: 10 | G91: =IFERROR(F91/E91,0) -> 1.1111111 | H91: 18 | I91: 7.03 | J91: =IFERROR(I91/H91,0) -> 0.39055556
A92: Dec 24 | B92: 48 | C92: 43 | D92: =IFERROR(C92/B92,0) -> 0.89583333 | E92: 8 | F92: 7 | G92: =IFERROR(F92/E92,0) -> 0.875 | H92: 16 | I92: 8.66 | J92: =IFERROR(I92/H92,0) -> 0.54125
A93: Jan 25 | B93: 55 | C93: 56 | D93: =IFERROR(C93/B93,0) -> 1.0181818 | E93: 9 | F93: 9 | G93: =IFERROR(F93/E93,0) -> 1 | H93: 18 | I93: 14.98 | J93: =IFERROR(I93/H93,0) -> 0.83222222
A94: Feb 25 | B94: 48 | C94: 44 | D94: =IFERROR(C94/B94,0) -> 0.91666667 | E94: 8 | F94: 7 | G94: =IFERROR(F94/E94,0) -> 0.875 | H94: 16 | I94: 13.61 | J94: =IFERROR(I94/H94,0) -> 0.850625
A95: Mar 25 | B95: 20 | C95: 12 | D95: =IFERROR(C95/B95,0) -> 0.6 | E95: 5 | F95: 2 | G95: =IFERROR(F95/E95,0) -> 0.4 | H95: 10 | I95: 13.93 | J95: =IFERROR(I95/H95,0) -> 1.393
A96: FY TOTAL | B96: =SUM(B84:B95) -> 547 | C96: =SUM(C84:C95) -> 500 | D96: =IFERROR(C96/B96,0) -> 0.91407678 | E96: =SUM(E84:E95) -> 93 | F96: =SUM(F84:F95) -> 85 | G96: =IFERROR(F96/E96,0) -> 0.91397849 | H96: =SUM(H84:H95) -> 187 | I96: =SUM(I84:I95) -> 122.69 | J96: =IFERROR(I96/H96,0) -> 0.65609626
A98: GODREJ PROPERTIES — REAL ESTATE SALES AUTOMATION SYSTEM | CONFIDENTIAL — FOR INTERNAL USE ONLY Area Sales Manager Dashboard | Formulas: XLOOKUP, INDEX-MATCH, SUMIFS, COUNTIFS, IFERROR, IF, TEXT, EOMONTH Generated: 22 June 2026 | CRM & Sales Operations | FY 2024-25

Sheet Lead Management
A1: 🏢 GODREJ PROPERTIES — LEAD MANAGEMENT REGISTER | 500 Records | FY 2024-25
A2: Real Estate Sales CRM | Auto-Tracking: Status, Follow-ups, Overdue Alerts | Updated: 22 Jun 2026
A3: Lead ID | B3: Lead Date | C3: Customer Name | D3: Mobile Number | E3: City | F3: Budget (₹) | G3: Project | H3: Unit Type | I3: Lead Source | J3: Assigned Executive | K3: Lead Status | L3: Last Call | M3: Next Follow-up | N3: Days Until F/U | O3: Reminder | P3: Channel Partner
A4: LD0001 | B4: 45662 | C4: Pooja Patel | D4: +91-8382514165 | E4: Thane | F4: 7400000 | G4: Godrej Summit | H4: 2BHK | I4: Facebook | J4: Priyanka Sharma | K4: Negotiation | L4: 45663 | M4: 46205 | N4: -10 | O4: On Track
A5: LD0002 | B5: 45715 | C5: Priya Joshi | D5: +91-7722368878 | E5: Hyderabad | F5: 21100000 | G5: Godrej Azure | H5: 4BHK | I5: Website | J5: Ravi Kumar | K5: Follow-up | L5: 45720 | M5: 46200 | N5: -5 | O5: On Track
A6: LD0003 | B6: 45555 | C6: Girish Choudhary | D6: +91-8244922676 | E6: Mumbai | F6: 29100000 | G6: Godrej Infinity | H6: Penthouse | I6: Google Ads | J6: Karan Singh | K6: Follow-up | L6: 45556 | M6: 46189 | N6: 6 | O6: OVERDUE
A7: LD0004 | B7: 45576 | C7: Geeta Mukherjee | D7: +91-9717792397 | E7: Kolkata | F7: 6000000 | G7: Godrej Summit | H7: 1BHK | I7: Referral | J7: Ravi Kumar | K7: New | L7: 45577 | M7: 46201 | N7: -6 | O7: On Track
A8: LD0005 | B8: 45423 | C8: Sunil Srinivasan | D8: +91-8245546434 | E8: Kolkata | F8: 23200000 | G8: Godrej Azure | H8: Penthouse | I8: Website | J8: Sneha Patel | K8: Booked | L8: 45425 | M8: 45426 | N8: 769 | O8: OVERDUE
A9: LD0006 | B9: 45714 | C9: Mohan Srinivasan | D9: +91-8750242087 | E9: Bangalore | F9: 11300000 | G9: Godrej Meridian | H9: 3BHK | I9: Channel Partner | J9: Karan Singh | K9: Negotiation | L9: 45715 | M9: 46206 | N9: -11 | O9: On Track | P9: Skyline Properties
A10: LD0007 | B10: 45411 | C10: Arun Desai | D10: +91-9637951347 | E10: Noida | F10: 33500000 | G10: Godrej Summit | H10: Penthouse | I10: Walk-in | J10: Sneha Patel | K10: Negotiation | L10: 45413 | M10: 46188 | N10: 7 | O10: OVERDUE
A11: LD0008 | B11: 45712 | C11: Santosh Choudhary | D11: +91-7867928301 | E11: Pune | F11: 18600000 | G11: Godrej Azure | H11: 4BHK | I11: Facebook | J11: Sunita Verma | K11: Site Visit Scheduled | L11: 45716 | M11: 46191 | N11: 4 | O11: OVERDUE
A12: LD0009 | B12: 45495 | C12: Rohit Chopra | D12: +91-8617121915 | E12: Ahmedabad | F12: 31800000 | G12: Godrej Summit | H12: Penthouse | I12: Referral | J12: Pooja Gupta | K12: Site Visit Scheduled | L12: 45497 | M12: 46203 | N12: -8 | O12: On Track
A13: LD0010 | B13: 45688 | C13: Neha Reddy | D13: +91-7823882512 | E13: Bangalore | F13: 29100000 | G13: Godrej Infinity | H13: Penthouse | I13: Walk-in | J13: Priyanka Sharma | K13: Site Visit Scheduled | L13: 45692 | M13: 46203 | N13: -8 | O13: On Track
A14: LD0011 | B14: 45615 | C14: Rahul Reddy | D14: +91-9869944522 | E14: Navi Mumbai | F14: 27700000 | G14: Godrej Summit | H14: Penthouse | I14: Website | J14: Karan Singh | K14: Site Visit Scheduled | L14: 45616 | M14: 46210 | N14: -15 | O14: On Track
A15: LD0012 | B15: 45461 | C15: Usha Mehta | D15: +91-8767479514 | E15: Ahmedabad | F15: 27000000 | G15: Godrej Reserve | H15: Penthouse | I15: Property Portal | J15: Ravi Kumar | K15: Site Visit Completed | L15: 45464 | M15: 46192 | N15: 3 | O15: OVERDUE
A16: LD0013 | B16: 45506 | C16: Rahul Taneja | D16: +91-7280673699 | E16: Delhi | F16: 4700000 | G16: Godrej Esteem | H16: 1BHK | I16: Google Ads | J16: Karan Singh | K16: Follow-up | L16: 45511 | M16: 46189 | N16: 6 | O16: OVERDUE
A17: LD0014 | B17: 45693 | C17: Suresh Bedi | D17: +91-8767136365 | E17: Bangalore | F17: 30000000 | G17: Godrej Infinity | H17: Penthouse | I17: Walk-in | J17: Rahul Nair | K17: Follow-up | L17: 45697 | M17: 46193 | N17: 2 | O17: OVERDUE
A18: LD0015 | B18: 45498 | C18: Aditya Venkatesh | D18: +91-7068987110 | E18: Navi Mumbai | F18: 15800000 | G18: Godrej Meridian | H18: 3BHK+Study | I18: Walk-in | J18: Sunita Verma | K18: New | L18: 45499 | M18: 46204 | N18: -9 | O18: On Track
A19: LD0016 | B19: 45399 | C19: Dinesh Agarwal | D19: +91-7912597684 | E19: Kolkata | F19: 4600000 | G19: Godrej Azure | H19: 1BHK | I19: Channel Partner | J19: Arjun Mehta | K19: Follow-up | L19: 45402 | M19: 46189 | N19: 6 | O19: OVERDUE | P19: Prime Location Brokers
A20: LD0017 | B20: 45625 | C20: Harish Verma | D20: +91-7309022704 | E20: Ahmedabad | F20: 31600000 | G20: Godrej Infinity | H20: Penthouse | I20: Walk-in | J20: Sunita Verma | K20: Follow-up | L20: 45629 | M20: 46193 | N20: 2 | O20: OVERDUE
A21: LD0018 | B21: 45713 | C21: Ravi Mukherjee | D21: +91-9386254473 | E21: Noida | F21: 15600000 | G21: Godrej Horizon | H21: 3BHK+Study | I21: Channel Partner | J21: Arjun Mehta | K21: Negotiation | L21: 45714 | M21: 46188 | N21: 7 | O21: OVERDUE | P21: Elite Property Group
A22: LD0019 | B22: 45619 | C22: Vijay Banerjee | D22: +91-8452082132 | E22: Hyderabad | F22: 19800000 | G22: Godrej Azure | H22: 4BHK | I22: Facebook | J22: Amit Joshi | K22: Follow-up | L22: 45621 | M22: 46189 | N22: 6 | O22: OVERDUE
A23: LD0020 | B23: 45631 | C23: Vijay Singh | D23: +91-9833262565 | E23: Navi Mumbai | F23: 6400000 | G23: Godrej Prime | H23: 1BHK | I23: Property Portal | J23: Sneha Patel | K23: Follow-up | L23: 45635 | M23: 46193 | N23: 2 | O23: OVERDUE
A24: LD0021 | B24: 45667 | C24: Neha Rao | D24: +91-7622248890 | E24: Noida | F24: 13100000 | G24: Godrej Prime | H24: 3BHK+Study | I24: Property Portal | J24: Sunita Verma | K24: Follow-up | L24: 45671 | M24: 46191 | N24: 4 | O24: OVERDUE
A25: LD0022 | B25: 45640 | C25: Sanjay Singh | D25: +91-7186376562 | E25: Kolkata | F25: 27300000 | G25: Godrej Prime | H25: Penthouse | I25: Website | J25: Arjun Mehta | K25: Site Visit Completed | L25: 45645 | M25: 46192 | N25: 3 | O25: OVERDUE
A26: LD0023 | B26: 45674 | C26: Anjali Mehta | D26: +91-8948115209 | E26: Pune | F26: 25900000 | G26: Godrej Reserve | H26: Penthouse | I26: Referral | J26: Priyanka Sharma | K26: Lost | L26: 45676 | M26: 45681 | N26: 514 | O26: OVERDUE
A27: LD0024 | B27: 45585 | C27: Sunil Joshi | D27: +91-8498251441 | E27: Noida | F27: 11200000 | G27: Godrej Meridian | H27: 3BHK | I27: Channel Partner | J27: Divya Reddy | K27: Follow-up | L27: 45587 | M27: 46208 | N27: -13 | O27: On Track | P27: Heritage Homes
A28: LD0025 | B28: 45561 | C28: Suresh Sharma | D28: +91-8210847353 | E28: Gurgaon | F28: 5600000 | G28: Godrej Reserve | H28: 1BHK | I28: Facebook | J28: Ravi Kumar | K28: Follow-up | L28: 45562 | M28: 46194 | N28: 1 | O28: OVERDUE
A29: LD0026 | B29: 45666 | C29: Arun Bhat | D29: +91-7339427601 | E29: Ahmedabad | F29: 21500000 | G29: Godrej Summit | H29: 4BHK | I29: Walk-in | J29: Arjun Mehta | K29: Negotiation | L29: 45669 | M29: 46208 | N29: -13 | O29: On Track
A30: LD0027 | B30: 45487 | C30: Kavita Reddy | D30: +91-8600842914 | E30: Pune | F30: 11900000 | G30: Godrej Infinity | H30: 3BHK | I30: Walk-in | J30: Sneha Patel | K30: Negotiation | L30: 45490 | M30: 46203 | N30: -8 | O30: On Track
A31: LD0028 | B31: 45709 | C31: Neha Joshi | D31: +91-9428867912 | E31: Navi Mumbai | F31: 9900000 | G31: Godrej Horizon | H31: 3BHK | I31: Website | J31: Divya Reddy | K31: Booked | L31: 45712 | M31: 45714 | N31: 481 | O31: OVERDUE
A32: LD0029 | B32: 45572 | C32: Dinesh Hegde | D32: +91-8408326704 | E32: Ahmedabad | F32: 4700000 | G32: Godrej Prime | H32: 1BHK | I32: Channel Partner | J32: Rahul Nair | K32: Site Visit Completed | L32: 45577 | M32: 46204 | N32: -9 | O32: On Track | P32: Skyline Properties
A33: LD0030 | B33: 45564 | C33: Amit Pandey | D33: +91-7775731299 | E33: Delhi | F33: 11300000 | G33: Godrej Prime | H33: 3BHK | I33: Channel Partner | J33: Sneha Patel | K33: Negotiation | L33: 45569 | M33: 46200 | N33: -5 | O33: On Track | P33: Skyline Properties
A34: LD0031 | B34: 45510 | C34: Deepa Naidu | D34: +91-9580024168 | E34: Mumbai | F34: 27600000 | G34: Godrej Infinity | H34: Penthouse | I34: Property Portal | J34: Amit Joshi | K34: Booked | L34: 45513 | M34: 45515 | N34: 680 | O34: OVERDUE
A35: LD0032 | B35: 45499 | C35: Divya Gupta | D35: +91-9162735313 | E35: Gurgaon | F35: 8400000 | G35: Godrej Azure | H35: 2BHK | I35: Google Ads | J35: Karan Singh | K35: Booked | L35: 45501 | M35: 45502 | N35: 693 | O35: OVERDUE
A36: LD0033 | B36: 45657 | C36: Santosh Bose | D36: +91-9873844237 | E36: Chennai | F36: 12400000 | G36: Godrej Reserve | H36: 3BHK | I36: Channel Partner | J36: Ravi Kumar | K36: Site Visit Scheduled | L36: 45660 | M36: 46187 | N36: 8 | O36: OVERDUE | P36: Urban Nest Advisors
A37: LD0034 | B37: 45543 | C37: Deepa Sethi | D37: +91-8675825157 | E37: Chennai | F37: 5800000 | G37: Godrej Prime | H37: 1BHK | I37: Referral | J37: Divya Reddy | K37: Booked | L37: 45547 | M37: 45552 | N37: 643 | O37: OVERDUE
A38: LD0035 | B38: 45658 | C38: Divya Arora | D38: +91-8413219171 | E38: Hyderabad | F38: 6000000 | G38: Godrej Summit | H38: 1BHK | I38: Referral | J38: Arjun Mehta | K38: Site Visit Completed | L38: 45660 | M38: 46198 | N38: -3 | O38: On Track
A39: LD0036 | B39: 45550 | C39: Naveen Grover | D39: +91-7968882667 | E39: Delhi | F39: 27000000 | G39: Godrej Reserve | H39: Penthouse | I39: Walk-in | J39: Karan Singh | K39: Negotiation | L39: 45554 | M39: 46209 | N39: -14 | O39: On Track
A40: LD0037 | B40: 45590 | C40: Rajesh Shah | D40: +91-7995747606 | E40: Noida | F40: 34600000 | G40: Godrej Horizon | H40: Penthouse | I40: Facebook | J40: Pooja Gupta | K40: Site Visit Completed | L40: 45595 | M40: 46187 | N40: 8 | O40: OVERDUE
A41: LD0038 | B41: 45469 | C41: Sanjay Hegde | D41: +91-8689097012 | E41: Kolkata | F41: 13900000 | G41: Godrej Meridian | H41: 3BHK+Study | I41: Referral | J41: Sneha Patel | K41: Site Visit Completed | L41: 45470 | M41: 46196 | N41: -1 | O41: On Track
A42: LD0039 | B42: 45406 | C42: Sunil Bose | D42: +91-9003019545 | E42: Pune | F42: 27200000 | G42: Godrej Azure | H42: Penthouse | I42: Facebook | J42: Sneha Patel | K42: New | L42: 45408 | M42: 46213 | N42: -18 | O42: On Track
A43: LD0040 | B43: 45458 | C43: Mohan Naidu | D43: +91-9550765724 | E43: Navi Mumbai | F43: 33700000 | G43: Godrej Azure | H43: Penthouse | I43: Referral | J43: Sunita Verma | K43: Site Visit Scheduled | L43: 45459 | M43: 46190 | N43: 5 | O43: OVERDUE
A44: LD0041 | B44: 45620 | C44: Meera Mehta | D44: +91-8951151588 | E44: Thane | F44: 5700000 | G44: Godrej Esteem | H44: 1BHK | I44: Facebook | J44: Priyanka Sharma | K44: Site Visit Scheduled | L44: 45625 | M44: 46204 | N44: -9 | O44: On Track
A45: LD0042 | B45: 45509 | C45: Anita Grover | D45: +91-8587992149 | E45: Thane | F45: 19700000 | G45: Godrej Horizon | H45: 4BHK | I45: Facebook | J45: Sunita Verma | K45: Site Visit Scheduled | L45: 45512 | M45: 46203 | N45: -8 | O45: On Track
A46: LD0043 | B46: 45659 | C46: Rohit Choudhary | D46: +91-7494240311 | E46: Gurgaon | F46: 26800000 | G46: Godrej Reserve | H46: Penthouse | I46: Facebook | J46: Karan Singh | K46: Follow-up | L46: 45660 | M46: 46191 | N46: 4 | O46: OVERDUE
A47: LD0044 | B47: 45595 | C47: Divya Iyer | D47: +91-9729265069 | E47: Thane | F47: 5400000 | G47: Godrej Azure | H47: 1BHK | I47: Referral | J47: Divya Reddy | K47: Site Visit Completed | L47: 45596 | M47: 46193 | N47: 2 | O47: OVERDUE
A48: LD0045 | B48: 45535 | C48: Divya Sethi | D48: +91-8763681582 | E48: Thane | F48: 19200000 | G48: Godrej Prime | H48: 4BHK | I48: Referral | J48: Arjun Mehta | K48: Lost | L48: 45539 | M48: 45543 | N48: 652 | O48: OVERDUE
... A55: LD0052 | B55: 45714 | C55: Vani Reddy | D55: +91-9783865057 | E55: Kolkata | F55: 14000000 | G55: Godrej Prime | H55: 3BHK | I55: Referral | J55: Divya Reddy | K55: New | L55: 45717 | M55: 46183 | N55: 12 | O55: OVERDUE
A56: LD0053 | B56: 45650 | C56: Harish Nair | D56: +91-8523267091 | E56: Noida | F56: 29700000 | G56: Godrej Meridian | H56: Penthouse | I56: Channel Partner | J56: Rahul Nair | K56: Site Visit Scheduled | L56: 45653 | M56: 46206 | N56: -11 | O56: On Track | P56: Metro Housing Services
A57: LD0054 | B57: 45674 | C57: Girish Choudhary | D57: +91-8102313761 | E57: Delhi | F57: 5100000 | G57: Godrej Azure | H57: 1BHK | I57: Referral | J57: Sneha Patel | K57: Booked | L57: 45679 | M57: 45683 | N57: 512 | O57: OVERDUE
A58: LD0055 | B58: 45688 | C58: Harish Das | D58: +91-7033277715 | E58: Bangalore | F58: 8000000 | G58: Godrej Esteem | H58: 2BHK | I58: Property Portal | J58: Karan Singh | K58: Follow-up | L58: 45691 | M58: 46204 | N58: -9 | O58: On Track
A59: LD0056 | B59: 45713 | C59: Kiran Joshi | D59: +91-9598212260 | E59: Hyderabad | F59: 14300000 | G59: Godrej Horizon | H59: 3BHK+Study | I59: Property Portal | J59: Sneha Patel | K59: Negotiation | L59: 45717 | M59: 46201 | N59: -6 | O59: On Track
A60: LD0057 | B60: 45666 | C60: Anjali Tiwari | D60: +91-8394282140 | E60: Hyderabad | F60: 26100000 | G60: Godrej Horizon | H60: Penthouse | I60: Google Ads | J60: Pooja Gupta | K60: Site Visit Scheduled | L60: 45671 | M60: 46198 | N60: -3 | O60: On Track
A61: LD0058 | B61: 45481 | C61: Naveen Mukherjee | D61: +91-9434280236 | E61: Thane | F61: 12100000 | G61: Godrej Esteem | H61: 3BHK | I61: Google Ads | J61: Sneha Patel | K61: New | L61: 45484 | M61: 46190 | N61: 5 | O61: OVERDUE
A62: LD0059 | B62: 45482 | C62: Deepa Shah | D62: +91-8182533519 | E62: Hyderabad | F62: 13900000 | G62: Godrej Esteem | H62: 3BHK | I62: Walk-in | J62: Karan Singh | K62: Lost | L62: 45485 | M62: 45487 | N62: 708 | O62: OVERDUE
A63: LD0060 | B63: 45447 | C63: Aditya Sharma | D63: +91-9859711607 | E63: Thane | F63: 9900000 | G63: Godrej Infinity | H63: 3BHK | I63: Website | J63: Ravi Kumar | K63: Follow-up | L63: 45451 | M63: 46190 | N63: 5 | O63: OVERDUE
A64: LD0061 | B64: 45627 | C64: Shobha Tiwari | D64: +91-8313074454 | E64: Gurgaon | F64: 13400000 | G64: Godrej Esteem | H64: 3BHK+Study | I64: Facebook | J64: Arjun Mehta | K64: Follow-up | L64: 45628 | M64: 46189 | N64: 6 | O64: OVERDUE
A65: LD0062 | B65: 45426 | C65: Suresh Arora | D65: +91-8828664548 | E65: Navi Mumbai | F65: 7100000 | G65: Godrej Prime | H65: 2BHK | I65: Property Portal | J65: Pooja Gupta | K65: Lost | L65: 45428 | M65: 45429 | N65: 766 | O65: OVERDUE
A66: LD0063 | B66: 45684 | C66: Vani Taneja | D66: +91-8863291399 | E66: Kolkata | F66: 19200000 | G66: Godrej Azure | H66: 4BHK | I66: Referral | J66: Sunita Verma | K66: Follow-up | L66: 45688 | M66: 46196 | N66: -1 | O66: On Track
A67: LD0064 | B67: 45463 | C67: Neha Grover | D67: +91-8808719838 | E67: Thane | F67: 9100000 | G67: Godrej Reserve | H67: 2BHK | I67: Facebook | J67: Karan Singh | K67: Negotiation | L67: 45465 | M67: 46192 | N67: 3 | O67: OVERDUE
A68: LD0065 | B68: 45530 | C68: Arun Sharma | D68: +91-7233240595 | E68: Noida | F68: 32000000 | G68: Godrej Esteem | H68: Penthouse | I68: Referral | J68: Karan Singh | K68: New | L68: 45533 | M68: 46212 | N68: -17 | O68: On Track
... A71: LD0068 | B71: 45500 | C71: Anjali Taneja | D71: +91-9505998117 | E71: Mumbai | F71: 27400000 | G71: Godrej Horizon | H71: Penthouse | I71: Walk-in | J71: Karan Singh | K71: New | L71: 45505 | M71: 46184 | N71: 11 | O71: OVERDUE
A72: LD0069 | B72: 45475 | C72: Manoj Arora | D72: +91-7298971605 | E72: Mumbai | F72: 14200000 | G72: Godrej Infinity | H72: 3BHK+Study | I72: Channel Partner | J72: Sunita Verma | K72: Lost | L72: 45480 | M72: 45484 | N72: 711 | O72: OVERDUE | P72: Metro Housing Services
A73: LD0070 | B73: 45636 | C73: Geeta Naidu | D73: +91-8312282102 | E73: Delhi | F73: 23800000 | G73: Godrej Meridian | H73: Penthouse | I73: Property Portal | J73: Rahul Nair | K73: Follow-up | L73: 45639 | M73: 46208 | N73: -13 | O73: On Track
A74: LD0071 | B74: 45383 | C74: Amit Desai | D74: +91-8354117104 | E74: Pune | F74: 12200000 | G74: Godrej Meridian | H74: 3BHK | I74: Website | J74: Amit Joshi | K74: Booked | L74: 45388 | M74: 45392 | N74: 803 | O74: OVERDUE
A75: LD0072 | B75: 45664 | C75: Kiran Kapoor | D75: +91-8435673532 | E75: Delhi | F75: 29400000 | G75: Godrej Esteem | H75: Penthouse | I75: Property Portal | J75: Arjun Mehta | K75: Follow-up | L75: 45666 | M75: 46196 | N75: -1 | O75: On Track
A76: LD0073 | B76: 45591 | C76: Pooja Patel | D76: +91-9757124871 | E76: Navi Mumbai | F76: 24700000 | G76: Godrej Azure | H76: Penthouse | I76: Google Ads | J76: Ravi Kumar | K76: New | L76: 45592 | M76: 46197 | N76: -2 | O76: On Track
A77: LD0074 | B77: 45522 | C77: Mohan Reddy | D77: +91-7798669871 | E77: Navi Mumbai | F77: 15900000 | G77: Godrej Infinity | H77: 3BHK+Study | I77: Channel Partner | J77: Karan Singh | K77: Site Visit Completed | L77: 45526 | M77: 46202 | N77: -7 | O77: On Track | P77: Metro Housing Services
A78: LD0075 | B78: 45524 | C78: Dinesh Iyer | D78: +91-9688710336 | E78: Noida | F78: 20300000 | G78: Godrej Azure | H78: 4BHK | I78: Channel Partner | J78: Rahul Nair | K78: Booked | L78: 45528 | M78: 45531 | N78: 664 | O78: OVERDUE | P78: Heritage Homes
A79: LD0076 | B79: 45665 | C79: Sneha Pandey | D79: +91-8492052176 | E79: Kolkata | F79: 8400000 | G79: Godrej Esteem | H79: 2BHK | I79: Walk-in | J79: Sunita Verma | K79: Follow-up | L79: 45670 | M79: 46199 | N79: -4 | O79: On Track
A80: LD0077 | B80: 45578 | C80: Kiran Banerjee | D80: +91-8623014852 | E80: Kolkata | F80: 8200000 | G80: Godrej Horizon | H80: 2BHK | I80: Website | J80: Divya Reddy | K80: Booked | L80: 45582 | M80: 45584 | N80: 611 | O80: OVERDUE
A81: LD0078 | B81: 45616 | C81: Rajesh Malhotra | D81: +91-8343495823 | E81: Kolkata | F81: 6300000 | G81: Godrej Meridian | H81: 1BHK | I81: Property Portal | J81: Sunita Verma | K81: New | L81: 45617 | M81: 46192 | N81: 3 | O81: OVERDUE
A82: LD0079 | B82: 45656 | C82: Sunita Kumar | D82: +91-9858680912 | E82: Gurgaon | F82: 12800000 | G82: Godrej Summit | H82: 3BHK | I82: Channel Partner | J82: Priyanka Sharma | K82: Booked | L82: 45660 | M82: 45663 | N82: 532 | O82: OVERDUE | P82: Metro Housing Services
A83: LD0080 | B83: 45605 | C83: Amit Grover | D83: +91-8453831805 | E83: Pune | F83: 33500000 | G83: Godrej Azure | H83: Penthouse | I83: Google Ads | J83: Sneha Patel | K83: Booked | L83: 45606 | M83: 45607 | N83: 588 | O83: OVERDUE
A84: LD0081 | B84: 45508 | C84: Aditya Patel | D84: +91-8854499364 | E84: Mumbai | F84: 5100000 | G84: Godrej Meridian | H84: 1BHK | I84: Google Ads | J84: Divya Reddy | K84: Site Visit Scheduled | L84: 45513 | M84: 46200 | N84: -5 | O84: On Track
A85: LD0082 | B85: 45681 | C85: Deepa Rao | D85: +91-8511093611 | E85: Bangalore | F85: 19200000 | G85: Godrej Reserve | H85: 4BHK | I85: Walk-in | J85: Sneha Patel | K85: Site Visit Completed | L85: 45683 | M85: 46194 | N85: 1 | O85: OVERDUE
A86: LD0083 | B86: 45609 | C86: Kavita Desai | D86: +91-7980293746 | E86: Chennai | F86: 15800000 | G86: Godrej Prime | H86: 3BHK+Study | I86: Google Ads | J86: Ravi Kumar | K86: Follow-up | L86: 45612 | M86: 46205 | N86: -10 | O86: On Track
A87: LD0084 | B87: 45578 | C87: Ravi Pillai | D87: +91-8883548780 | E87: Gurgaon | F87: 8100000 | G87: Godrej Summit | H87: 2BHK | I87: Property Portal | J87: Sunita Verma | K87: New | L87: 45583 | M87: 46205 | N87: -10 | O87: On Track
A88: LD0085 | B88: 45637 | C88: Sneha Patel | D88: +91-8989256179 | E88: Navi Mumbai | F88: 9600000 | G88: Godrej Horizon | H88: 3BHK | I88: Walk-in | J88: Arjun Mehta | K88: Lost | L88: 45640 | M88: 45642 | N88: 553 | O88: OVERDUE
A89: LD0086 | B89: 45704 | C89: Meera Shah | D89: +91-7109385965 | E89: Kolkata | F89: 34700000 | G89: Godrej Summit | H89: Penthouse | I89: Channel Partner | J89: Rahul Nair | K89: Negotiation | L89: 45705 | M89: 46196 | N89: -1 | O89: On Track | P89: Metro Housing Services
A90: LD0087 | B90: 45659 | C90: Vivek Mishra | D90: +91-9993345720 | E90: Pune | F90: 13000000 | G90: Godrej Summit | H90: 3BHK | I90: Facebook | J90: Sneha Patel | K90: New | L90: 45662 | M90: 46215 | N90: -20 | O90: On Track
A91: LD0088 | B91: 45421 | C91: Arun Pillai | D91: +91-9818598647 | E91: Gurgaon | F91: 27700000 | G91: Godrej Summit | H91: Penthouse | I91: Property Portal | J91: Priyanka Sharma | K91: Site Visit Scheduled | L91: 45423 | M91: 46194 | N91: 1 | O91: OVERDUE
A92: LD0089 | B92: 45571 | C92: Santosh Chopra | D92: +91-9694893695 | E92: Delhi | F92: 12100000 | G92: Godrej Reserve | H92: 3BHK+Study | I92: Google Ads | J92: Ravi Kumar | K92: New | L92: 45574 | M92: 46207 | N92: -12 | O92: On Track
A93: LD0090 | B93: 45695 | C93: Vivek Nair | D93: +91-7207193283 | E93: Navi Mumbai | F93: 12100000 | G93: Godrej Azure | H93: 3BHK+Study | I93: Walk-in | J93: Ravi Kumar | K93: Follow-up | L93: 45697 | M93: 46207 | N93: -12 | O93: On Track
A94: LD0091 | B94: 45635 | C94: Mohan Pandey | D94: +91-7769380457 | E94: Navi Mumbai | F94: 4800000 | G94: Godrej Horizon | H94: 1BHK | I94: Website | J94: Arjun Mehta | K94: Follow-up | L94: 45636 | M94: 46190 | N94: 5 | O94: OVERDUE
A95: LD0092 | B95: 45462 | C95: Rajesh Krishnan | D95: +91-9731874139 | E95: Gurgaon | F95: 34500000 | G95: Godrej Meridian | H95: Penthouse | I95: Channel Partner | J95: Ravi Kumar | K95: Site Visit Scheduled | L95: 45466 | M95: 46207 | N95: -12 | O95: On Track | P95: Urban Nest Advisors
A96: LD0093 | B96: 45503 | C96: Sunil Naidu | D96: +91-9246858147 | E96: Chennai | F96: 28200000 | G96: Godrej Prime | H96: Penthouse | I96: Facebook | J96: Sunita Verma | K96: Site Visit Scheduled | L96: 45506 | M96: 46190 | N96: 5 | O96: OVERDUE
A97: LD0094 | B97: 45491 | C97: Poonam Mukherjee | D97: +91-7165753713 | E97: Mumbai | F97: 11100000 | G97: Godrej Horizon | H97: 3BHK | I97: Website | J97: Sunita Verma | K97: New | L97: 45496 | M97: 46184 | N97: 11 | O97: OVERDUE
A98: LD0095 | B98: 45493 | C98: Rohit Mishra | D98: +91-9537429340 | E98: Kolkata | F98: 6200000 | G98: Godrej Azure | H98: 1BHK | I98: Property Portal | J98: Ravi Kumar | K98: Follow-up | L98: 45495 | M98: 46197 | N98: -2 | O98: On Track
A99: LD0096 | B99: 45396 | C99: Vani Sharma | D99: +91-8173841186 | E99: Chennai | F99: 8800000 | G99: Godrej Infinity | H99: 2BHK | I99: Google Ads | J99: Rahul Nair | K99: New | L99: 45398 | M99: 46183 | N99: 12 | O99: OVERDUE
A100: LD0097 | B100: 45415 | C100: Girish Das | D100: +91-9549457453 | E100: Mumbai | F100: 9900000 | G100: Godrej Infinity | H100: 3BHK | I100: Facebook | J100: Amit Joshi | K100: Site Visit Completed | L100: 45419 | M100: 46201 | N100: -6 | O100: On Track
A101: LD0098 | B101: 45720 | C101: Usha Sethi | D101: +91-8500994323 | E101: Pune | F101: 17900000 | G101: Godrej Esteem | H101: 4BHK | I101: Walk-in | J101: Arjun Mehta | K101: Booked | L101: 45725 | M101: 45728 | N101: 467 | O101: OVERDUE
A102: LD0099 | B102: 45610 | C102: Priya Singh | D102: +91-8055489730 | E102: Gurgaon | F102: 14900000 | G102: Godrej Horizon | H102: 3BHK+Study | I102: Website | J102: Sunita Verma | K102: Negotiation | L102: 45611 | M102: 46189 | N102: 6 | O102: OVERDUE
A103: LD0100 | B103: 45578 | C103: Sunita Kumar | D103: +91-7966369469 | E103: Bangalore | F103: 21300000 | G103: Godrej Summit | H103: 4BHK | I103: Walk-in | J103: Ravi Kumar | K103: Negotiation | L103: 45583 | M103: 46203 | N103: -8 | O103: On Track
A104: LD0101 | B104: 45493 | C104: Usha Taneja | D104: +91-9910039949 | E104: Noida | F104: 23900000 | G104: Godrej Reserve | H104: Penthouse | I104: Property Portal | J104: Ravi Kumar | K104: Booked | L104: 45497 | M104: 45501 | N104: 694 | O104: OVERDUE
A105: LD0102 | B105: 45723 | C105: Lakshmi Bose | D105: +91-7500172163 | E105: Gurgaon | F105: 15100000 | G105: Godrej Horizon | H105: 3BHK+Study | I105: Website | J105: Divya Reddy | K105: Site Visit Scheduled | L105: 45726 | M105: 46198 | N105: -3 | O105: On Track
A106: LD0103 | B106: 45667 | C106: Suresh Joshi | D106: +91-9195426021 | E106: Pune | F106: 12400000 | G106: Godrej Reserve | H106: 3BHK+Study | I106: Channel Partner | J106: Divya Reddy | K106: Booked | L106: 45668 | M106: 45673 | N106: 522 | O106: OVERDUE | P106: Apex Realty Solutions
A107: LD0104 | B107: 45436 | C107: Lakshmi Mukherjee | D107: +91-7697130280 | E107: Navi Mumbai | F107: 22900000 | G107: Godrej Horizon | H107: Penthouse | I107: Google Ads | J107: Pooja Gupta | K107: Follow-up | L107: 45441 | M107: 46203 | N107: -8 | O107: On Track
A108: LD0105 | B108: 45602 | C108: Sheela Agarwal | D108: +91-9010598470 | E108: Pune | F108: 19100000 | G108: Godrej Meridian | H108: 4BHK | I108: Website | J108: Karan Singh | K108: Site Visit Completed | L108: 45607 | M108: 46206 | N108: -11 | O108: On Track
...

Sheet Executive Performance
A1: 🏆 SALES EXECUTIVE PERFORMANCE SCORECARD | Auto-calculated KPIs | FY 2024-25
A2: Live from Lead Management & Booking data | COUNTIFS / SUMIFS auto-tracking
A3: Rank | B3: Executive Name | C3: Leads Assigned | D3: Calls Made | E3: Site Visits | F3: Bookings | G3: Revenue (₹) | H3: Conversion % | I3: Avg Deal Size (₹) | J3: Rating
A4: =IFERROR(RANK(G4,G$4:G$13,0),"-") -> 7 | B4: Arjun Mehta | C4: =COUNTIFS('Lead Management'!$J$4:$J$503,B4) -> 39 | D4: =ROUND(C4*4.2,0) -> 164 | E4: =COUNTIFS('Lead Management'!$J$4:$J$503,B4,'Lead Management'!$K$4:$K$503,"Site Visit Completed")+COUNTIFS('Lead Management'!$J$4:$J$503,B4,'Lead Management'!$K$4:$K$503,"Booked")+COUNTIFS('Lead Management'!$J$4:$J$503,B4,'Lead Management'!$K$4:$K$503,"Negotiation") -> 18 | F4: =COUNTIFS('Lead Management'!$J$4:$J$503,B4,'Lead Management'!$K$4:$K$503,"Booked") -> 6 | G4: =SUMIFS('Booking Management'!$E$4:$E$200,'Booking Management'!$H$4:$H$200,B4) -> 85990000 | H4: =IFERROR(F4/C4,0) -> 0.15384615 | I4: =IFERROR(G4/F4,0) -> 14331667 | J4: =IF(H4>=0.25,"⭐ Star",IF(H4>=0.15,"✅ Good",IF(H4>=0.08,"⚠ Average","❌ Below Target"))) -> ✅ Good
A5: =IFERROR(RANK(G5,G$4:G$13,0),"-") -> 2 | B5: Priyanka Sharma | C5: =COUNTIFS('Lead Management'!$J$4:$J$503,B5) -> 48 | D5: =ROUND(C5*3.8,0) -> 182 | E5: =COUNTIFS('Lead Management'!$J$4:$J$503,B5,'Lead Management'!$K$4:$K$503,"Site Visit Completed")+COUNTIFS('Lead Management'!$J$4:$J$503,B5,'Lead Management'!$K$4:$K$503,"Booked")+COUNTIFS('Lead Management'!$J$4:$J$503,B5,'Lead Management'!$K$4:$K$503,"Negotiation") -> 18 | F5: =COUNTIFS('Lead Management'!$J$4:$J$503,B5,'Lead Management'!$K$4:$K$503,"Booked") -> 11 | G5: =SUMIFS('Booking Management'!$E$4:$E$200,'Booking Management'!$H$4:$H$200,B5) -> 181730000 | H5: =IFERROR(F5/C5,0) -> 0.22916667 | I5: =IFERROR(G5/F5,0) -> 16520909 | J5: =IF(H5>=0.25,"⭐ Star",IF(H5>=0.15,"✅ Good",IF(H5>=0.08,"⚠ Average","❌ Below Target"))) -> ✅ Good
A6: =IFERROR(RANK(G6,G$4:G$13,0),"-") -> 9 | B6: Rahul Nair | C6: =COUNTIFS('Lead Management'!$J$4:$J$503,B6) -> 52 | D6: =ROUND(C6*4.5,0) -> 234 | E6: =COUNTIFS('Lead Management'!$J$4:$J$503,B6,'Lead Management'!$K$4:$K$503,"Site Visit Completed")+COUNTIFS('Lead Management'!$J$4:$J$503,B6,'Lead Management'!$K$4:$K$503,"Booked")+COUNTIFS('Lead Management'!$J$4:$J$503,B6,'Lead Management'!$K$4:$K$503,"Negotiation") -> 22 | F6: =COUNTIFS('Lead Management'!$J$4:$J$503,B6,'Lead Management'!$K$4:$K$503,"Booked") -> 6 | G6: =SUMIFS('Booking Management'!$E$4:$E$200,'Booking Management'!$H$4:$H$200,B6) -> 70510000 | H6: =IFERROR(F6/C6,0) -> 0.11538462 | I6: =IFERROR(G6/F6,0) -> 11751667 | J6: =IF(H6>=0.25,"⭐ Star",IF(H6>=0.15,"✅ Good",IF(H6>=0.08,"⚠ Average","❌ Below Target"))) -> ⚠ Average
A7: =IFERROR(RANK(G7,G$4:G$13,0),"-") -> 1 | B7: Sneha Patel | C7: =COUNTIFS('Lead Management'!$J$4:$J$503,B7) -> 57 | D7: =ROUND(C7*3.6,0) -> 205 | E7: =COUNTIFS('Lead Management'!$J$4:$J$503,B7,'Lead Management'!$K$4:$K$503,"Site Visit Completed")+COUNTIFS('Lead Management'!$J$4:$J$503,B7,'Lead Management'!$K$4:$K$503,"Booked")+COUNTIFS('Lead Management'!$J$4:$J$503,B7,'Lead Management'!$K$4:$K$503,"Negotiation") -> 38 | F7: =COUNTIFS('Lead Management'!$J$4:$J$503,B7,'Lead Management'!$K$4:$K$503,"Booked") -> 14 | G7: =SUMIFS('Booking Management'!$E$4:$E$200,'Booking Management'!$H$4:$H$200,B7) -> 188760000 | H7: =IFERROR(F7/C7,0) -> 0.24561404 | I7: =IFERROR(G7/F7,0) -> 13482857 | J7: =IF(H7>=0.25,"⭐ Star",IF(H7>=0.15,"✅ Good",IF(H7>=0.08,"⚠ Average","❌ Below Target"))) -> ✅ Good
A8: =IFERROR(RANK(G8,G$4:G$13,0),"-") -> 4 | B8: Karan Singh | C8: =COUNTIFS('Lead Management'!$J$4:$J$503,B8) -> 61 | D8: =ROUND(C8*4.1,0) -> 250 | E8: =COUNTIFS('Lead Management'!$J$4:$J$503,B8,'Lead Management'!$K$4:$K$503,"Site Visit Completed")+COUNTIFS('Lead Management'!$J$4:$J$503,B8,'Lead Management'!$K$4:$K$503,"Booked")+COUNTIFS('Lead Management'!$J$4:$J$503,B8,'Lead Management'!$K$4:$K$503,"Negotiation") -> 28 | F8: =COUNTIFS('Lead Management'!$J$4:$J$503,B8,'Lead Management'!$K$4:$K$503,"Booked") -> 12 | G8: =SUMIFS('Booking Management'!$E$4:$E$200,'Booking Management'!$H$4:$H$200,B8) -> 174890000 | H8: =IFERROR(F8/C8,0) -> 0.19672131 | I8: =IFERROR(G8/F8,0) -> 14574167 | J8: =IF(H8>=0.25,"⭐ Star",IF(H8>=0.15,"✅ Good",IF(H8>=0.08,"⚠ Average","❌ Below Target"))) -> ✅ Good
A9: =IFERROR(RANK(G9,G$4:G$13,0),"-") -> 3 | B9: Divya Reddy | C9: =COUNTIFS('Lead Management'!$J$4:$J$503,B9) -> 49 | D9: =ROUND(C9*3.9,0) -> 191 | E9: =COUNTIFS('Lead Management'!$J$4:$J$503,B9,'Lead Management'!$K$4:$K$503,"Site Visit Completed")+COUNTIFS('Lead Management'!$J$4:$J$503,B9,'Lead Management'!$K$4:$K$503,"Booked")+COUNTIFS('Lead Management'!$J$4:$J$503,B9,'Lead Management'!$K$4:$K$503,"Negotiation") -> 24 | F9: =COUNTIFS('Lead Management'!$J$4:$J$503,B9,'Lead Management'!$K$4:$K$503,"Booked") -> 14 | G9: =SUMIFS('Booking Management'!$E$4:$E$200,'Booking Management'!$H$4:$H$200,B9) -> 179070000 | H9: =IFERROR(F9/C9,0) -> 0.28571429 | I9: =IFERROR(G9/F9,0) -> 12790714 | J9: =IF(H9>=0.25,"⭐ Star",IF(H9>=0.15,"✅ Good",IF(H9>=0.08,"⚠ Average","❌ Below Target"))) -> ⭐ Star
A10: =IFERROR(RANK(G10,G$4:G$13,0),"-") -> 6 | B10: Amit Joshi | C10: =COUNTIFS('Lead Management'!$J$4:$J$503,B10) -> 39 | D10: =ROUND(C10*4.3,0) -> 168 | E10: =COUNTIFS('Lead Management'!$J$4:$J$503,B10,'Lead Management'!$K$4:$K$503,"Site Visit Completed")+COUNTIFS('Lead Management'!$J$4:$J$503,B10,'Lead Management'!$K$4:$K$503,"Booked")+COUNTIFS('Lead Management'!$J$4:$J$503,B10,'Lead Management'!$K$4:$K$503,"Negotiation") -> 18 | F10: =COUNTIFS('Lead Management'!$J$4:$J$503,B10,'Lead Management'!$K$4:$K$503,"Booked") -> 4 | G10: =SUMIFS('Booking Management'!$E$4:$E$200,'Booking Management'!$H$4:$H$200,B10) -> 88960000 | H10: =IFERROR(F10/C10,0) -> 0.1025641 | I10: =IFERROR(G10/F10,0) -> 22240000 | J10: =IF(H10>=0.25,"⭐ Star",IF(H10>=0.15,"✅ Good",IF(H10>=0.08,"⚠ Average","❌ Below Target"))) -> ⚠ Average
A11: =IFERROR(RANK(G11,G$4:G$13,0),"-") -> 10 | B11: Sunita Verma | C11: =COUNTIFS('Lead Management'!$J$4:$J$503,B11) -> 43 | D11: =ROUND(C11*3.7,0) -> 159 | E11: =COUNTIFS('Lead Management'!$J$4:$J$503,B11,'Lead Management'!$K$4:$K$503,"Site Visit Completed")+COUNTIFS('Lead Management'!$J$4:$J$503,B11,'Lead Management'!$K$4:$K$503,"Booked")+COUNTIFS('Lead Management'!$J$4:$J$503,B11,'Lead Management'!$K$4:$K$503,"Negotiation") -> 14 | F11: =COUNTIFS('Lead Management'!$J$4:$J$503,B11,'Lead Management'!$K$4:$K$503,"Booked") -> 4 | G11: =SUMIFS('Booking Management'!$E$4:$E$200,'Booking Management'!$H$4:$H$200,B11) -> 42830000 | H11: =IFERROR(F11/C11,0) -> 0.093023256 | I11: =IFERROR(G11/F11,0) -> 10707500 | J11: =IF(H11>=0.25,"⭐ Star",IF(H11>=0.15,"✅ Good",IF(H11>=0.08,"⚠ Average","❌ Below Target"))) -> ⚠ Average
A12: =IFERROR(RANK(G12,G$4:G$13,0),"-") -> 5 | B12: Ravi Kumar | C12: =COUNTIFS('Lead Management'!$J$4:$J$503,B12) -> 55 | D12: =ROUND(C12*4,0) -> 220 | E12: =COUNTIFS('Lead Management'!$J$4:$J$503,B12,'Lead Management'!$K$4:$K$503,"Site Visit Completed")+COUNTIFS('Lead Management'!$J$4:$J$503,B12,'Lead Management'!$K$4:$K$503,"Booked")+COUNTIFS('Lead Management'!$J$4:$J$503,B12,'Lead Management'!$K$4:$K$503,"Negotiation") -> 19 | F12: =COUNTIFS('Lead Management'!$J$4:$J$503,B12,'Lead Management'!$K$4:$K$503,"Booked") -> 7 | G12: =SUMIFS('Booking Management'!$E$4:$E$200,'Booking Management'!$H$4:$H$200,B12) -> 132620000 | H12: =IFERROR(F12/C12,0) -> 0.12727273 | I12: =IFERROR(G12/F12,0) -> 18945714 | J12: =IF(H12>=0.25,"⭐ Star",IF(H12>=0.15,"✅ Good",IF(H12>=0.08,"⚠ Average","❌ Below Target"))) -> ⚠ Average
A13: =IFERROR(RANK(G13,G$4:G$13,0),"-") -> 8 | B13: Pooja Gupta | C13: =COUNTIFS('Lead Management'!$J$4:$J$503,B13) -> 57 | D13: =ROUND(C13*4.4,0) -> 251 | E13: =COUNTIFS('Lead Management'!$J$4:$J$503,B13,'Lead Management'!$K$4:$K$503,"Site Visit Completed")+COUNTIFS('Lead Management'!$J$4:$J$503,B13,'Lead Management'!$K$4:$K$503,"Booked")+COUNTIFS('Lead Management'!$J$4:$J$503,B13,'Lead Management'!$K$4:$K$503,"Negotiation") -> 21 | F13: =COUNTIFS('Lead Management'!$J$4:$J$503,B13,'Lead Management'!$K$4:$K$503,"Booked") -> 7 | G13: =SUMIFS('Booking Management'!$E$4:$E$200,'Booking Management'!$H$4:$H$200,B13) -> 81280000 | H13: =IFERROR(F13/C13,0) -> 0.12280702 | I13: =IFERROR(G13/F13,0) -> 11611429 | J13: =IF(H13>=0.25,"⭐ Star",IF(H13>=0.15,"✅ Good",IF(H13>=0.08,"⚠ Average","❌ Below Target"))) -> ⚠ Average
A15: TEAM TOTAL / AVG | C15: =SUM(C4:C13) -> 500 | D15: =SUM(D4:D13) -> 2024 | E15: =SUM(E4:E13) -> 220 | F15: =SUM(F4:F13) -> 85 | G15: =SUM(G4:G13) -> 1226640000 | H15: =IFERROR(F15/C15,0) -> 0.17 | I15: =IFERROR(G15/F15,0) -> 14431059
A18: 🔍 XLOOKUP / INDEX-MATCH EXECUTIVE DRILL-DOWN — Type any executive name in B20
B19: Executive → | C19: Leads | D19: Calls | E19: Site Visits | F19: Bookings | G19: Revenue (₹) | H19: Conv% | I19: Avg Deal | J19: Rating
B20: Arjun Mehta | C20: =IFERROR(INDEX(C$4:C$13,MATCH($B$20,$B$4:$B$13,0)),"—") -> 39 | D20: =IFERROR(INDEX(D$4:D$13,MATCH($B$20,$B$4:$B$13,0)),"—") -> 164 | E20: =IFERROR(INDEX(E$4:E$13,MATCH($B$20,$B$4:$B$13,0)),"—") -> 18 | F20: =IFERROR(INDEX(F$4:F$13,MATCH($B$20,$B$4:$B$13,0)),"—") -> 6 | G20: =IFERROR(INDEX(G$4:G$13,MATCH($B$20,$B$4:$B$13,0)),"—") -> 85990000 | H20: =IFERROR(INDEX(H$4:H$13,MATCH($B$20,$B$4:$B$13,0)),"—") -> 0.15384615 | I20: =IFERROR(INDEX(I$4:I$13,MATCH($B$20,$B$4:$B$13,0)),"—") -> 14331667 | J20: =IFERROR(INDEX(J$4:J$13,MATCH($B$20,$B$4:$B$13,0)),"—") -> ✅ Good
A21: Formula: =INDEX([return_range], MATCH($B$20, $B$4:$B$13, 0)) | Change executive name in B20 to fetch any executive's full scorecard

Sheet Booking Management
A1: 📋 BOOKING MANAGEMENT — CONFIRMED SALES REGISTER | 85 Bookings | FY 2024-25
A2: Confirmed Transactions | Linked to Lead Management | Revenue Tracking
A3: Booking ID | B3: Customer Name | C3: Project | D3: Unit Type | E3: Property Value (₹) | F3: Booking Amount (₹) | G3: Booking Date | H3: Executive | I3: City | J3: Lead Source | K3: Channel Partner
A4: BK0001 | B4: Sunil Srinivasan | C4: Godrej Azure | D4: Penthouse | E4: 30140000 | F4: 2629000 | G4: 45471 | H4: Sneha Patel | I4: Kolkata | J4: Website
A5: BK0002 | B5: Neha Joshi | C5: Godrej Horizon | D5: 3BHK | E5: 12380000 | F5: 1478000 | G5: 45733 | H5: Divya Reddy | I5: Navi Mumbai | J5: Website
A6: BK0003 | B6: Deepa Naidu | C6: Godrej Infinity | D6: Penthouse | E6: 35790000 | F6: 3084000 | G6: 45556 | H6: Amit Joshi | I6: Mumbai | J6: Property Portal
A7: BK0004 | B7: Divya Gupta | C7: Godrej Azure | D7: 2BHK | E7: 8230000 | F7: 912000 | G7: 45529 | H7: Karan Singh | I7: Gurgaon | J7: Google Ads
A8: BK0005 | B8: Deepa Sethi | C8: Godrej Prime | D8: 1BHK | E8: 5200000 | F8: 460000 | G8: 45580 | H8: Divya Reddy | I8: Chennai | J8: Referral
A9: BK0006 | B9: Poonam Patel | C9: Godrej Prime | D9: 1BHK | E9: 5610000 | F9: 618000 | G9: 45498 | H9: Rahul Nair | I9: Noida | J9: Referral
A10: BK0007 | B10: Rajesh Jain | C10: Godrej Reserve | D10: 4BHK | E10: 19890000 | F10: 1908000 | G10: 45502 | H10: Karan Singh | I10: Navi Mumbai | J10: Referral
A11: BK0008 | B11: Girish Choudhary | C11: Godrej Azure | D11: 1BHK | E11: 6730000 | F11: 601000 | G11: 45732 | H11: Sneha Patel | I11: Delhi | J11: Referral
A12: BK0009 | B12: Amit Desai | C12: Godrej Meridian | D12: 3BHK | E12: 13480000 | F12: 1220000 | G12: 45431 | H12: Amit Joshi | I12: Pune | J12: Website
A13: BK0010 | B13: Dinesh Iyer | C13: Godrej Azure | D13: 4BHK | E13: 16100000 | F13: 1474000 | G13: 45567 | H13: Rahul Nair | I13: Noida | J13: Channel Partner | K13: Heritage Homes
A14: BK0011 | B14: Kiran Banerjee | C14: Godrej Horizon | D14: 2BHK | E14: 7820000 | F14: 926000 | G14: 45636 | H14: Divya Reddy | I14: Kolkata | J14: Website
A15: BK0012 | B15: Sunita Kumar | C15: Godrej Summit | D15: 3BHK | E15: 10320000 | F15: 1204000 | G15: 45711 | H15: Priyanka Sharma | I15: Gurgaon | J15: Channel Partner | K15: Metro Housing Services
A16: BK0013 | B16: Amit Grover | C16: Godrej Azure | D16: Penthouse | E16: 36160000 | F16: 3517000 | G16: 45661 | H16: Sneha Patel | I16: Pune | J16: Google Ads
A17: BK0014 | B17: Usha Sethi | C17: Godrej Esteem | D17: 4BHK | E17: 18810000 | F17: 1708000 | G17: 45741 | H17: Arjun Mehta | I17: Pune | J17: Walk-in
A18: BK0015 | B18: Usha Taneja | C18: Godrej Reserve | D18: Penthouse | E18: 31800000 | F18: 3042000 | G18: 45551 | H18: Ravi Kumar | I18: Noida | J18: Property Portal
A19: BK0016 | B19: Suresh Joshi | C19: Godrej Reserve | D19: 3BHK+Study | E19: 13640000 | F19: 1375000 | G19: 45725 | H19: Divya Reddy | I19: Pune | J19: Channel Partner | K19: Apex Realty Solutions
A20: BK0017 | B20: Shobha Venkatesh | C20: Godrej Infinity | D20: Penthouse | E20: 25020000 | F20: 2315000 | G20: 45508 | H20: Priyanka Sharma | I20: Pune | J20: Website
A21: BK0018 | B21: Geeta Kumar | C21: Godrej Prime | D21: 3BHK+Study | E21: 12570000 | F21: 1012000 | G21: 45698 | H21: Priyanka Sharma | I21: Noida | J21: Referral
A22: BK0019 | B22: Rohit Hegde | C22: Godrej Horizon | D22: 4BHK | E22: 21750000 | F22: 2128000 | G22: 45525 | H22: Karan Singh | I22: Kolkata | J22: Referral
A23: BK0020 | B23: Rekha Iyer | C23: Godrej Reserve | D23: 3BHK+Study | E23: 14110000 | F23: 1238000 | G23: 45701 | H23: Karan Singh | I23: Gurgaon | J23: Channel Partner | K23: Urban Nest Advisors
A24: BK0021 | B24: Sunil Mishra | C24: Godrej Horizon | D24: 2BHK | E24: 6740000 | F24: 792000 | G24: 45524 | H24: Pooja Gupta | I24: Kolkata | J24: Facebook
A25: BK0022 | B25: Anita Desai | C25: Godrej Horizon | D25: 4BHK | E25: 17820000 | F25: 2103000 | G25: 45747 | H25: Rahul Nair | I25: Chennai | J25: Referral
A26: BK0023 | B26: Anjali Srinivasan | C26: Godrej Prime | D26: 3BHK | E26: 10510000 | F26: 877000 | G26: 45506 | H26: Divya Reddy | I26: Hyderabad | J26: Property Portal
A27: BK0024 | B27: Rajesh Jain | C27: Godrej Prime | D27: 1BHK | E27: 5270000 | F27: 610000 | G27: 45722 | H27: Sneha Patel | I27: Gurgaon | J27: Google Ads
A28: BK0025 | B28: Vivek Pillai | C28: Godrej Prime | D28: 3BHK | E28: 11970000 | F28: 1181000 | G28: 45723 | H28: Sneha Patel | I28: Thane | J28: Google Ads
A29: BK0026 | B29: Kiran Tiwari | C29: Godrej Prime | D29: Penthouse | E29: 26640000 | F29: 2951000 | G29: 45665 | H29: Priyanka Sharma | I29: Delhi | J29: Google Ads
A30: BK0027 | B30: Naveen Mehta | C30: Godrej Esteem | D30: 3BHK | E30: 12210000 | F30: 1102000 | G30: 45442 | H30: Priyanka Sharma | I30: Gurgaon | J30: Google Ads
A31: BK0028 | B31: Vani Jain | C31: Godrej Prime | D31: 1BHK | E31: 4760000 | F31: 454000 | G31: 45625 | H31: Karan Singh | I31: Chennai | J31: Facebook
A32: BK0029 | B32: Pooja Mishra | C32: Godrej Horizon | D32: 3BHK | E32: 11670000 | F32: 1380000 | G32: 45515 | H32: Divya Reddy | I32: Pune | J32: Walk-in
A33: BK0030 | B33: Pooja Mehta | C33: Godrej Horizon | D33: 4BHK | E33: 16580000 | F33: 1653000 | G33: 45421 | H33: Sneha Patel | I33: Ahmedabad | J33: Channel Partner | K33: Elite Property Group
A34: BK0031 | B34: Ramesh Agarwal | C34: Godrej Summit | D34: 3BHK | E34: 11000000 | F34: 1164000 | G34: 45493 | H34: Pooja Gupta | I34: Noida | J34: Walk-in
A35: BK0032 | B35: Geeta Pandey | C35: Godrej Meridian | D35: 4BHK | E35: 22450000 | F35: 2183000 | G35: 45677 | H35: Priyanka Sharma | I35: Chennai | J35: Referral
A36: BK0033 | B36: Shobha Gupta | C36: Godrej Meridian | D36: 1BHK | E36: 6350000 | F36: 690000 | G36: 45607 | H36: Rahul Nair | I36: Bangalore | J36: Walk-in
A37: BK0034 | B37: Rohit Arora | C37: Godrej Meridian | D37: 3BHK+Study | E37: 12590000 | F37: 1295000 | G37: 45454 | H37: Rahul Nair | I37: Noida | J37: Channel Partner | K37: Prop World Realty
A38: BK0035 | B38: Meera Kumar | C38: Godrej Horizon | D38: 3BHK | E38: 9660000 | F38: 1119000 | G38: 45637 | H38: Karan Singh | I38: Delhi | J38: Channel Partner | K38: Apex Realty Solutions
A39: BK0036 | B39: Ravi Mehta | C39: Godrej Horizon | D39: 1BHK | E39: 4500000 | F39: 528000 | G39: 45477 | H39: Karan Singh | I39: Navi Mumbai | J39: Walk-in
A40: BK0037 | B40: Dinesh Patel | C40: Godrej Esteem | D40: Penthouse | E40: 24540000 | F40: 2650000 | G40: 45458 | H40: Karan Singh | I40: Thane | J40: Referral
A41: BK0038 | B41: Santosh Mehta | C41: Godrej Horizon | D41: 3BHK+Study | E41: 16320000 | F41: 1768000 | G41: 45659 | H41: Pooja Gupta | I41: Bangalore | J41: Channel Partner | K41: Elite Property Group
A42: BK0039 | B42: Dinesh Malhotra | C42: Godrej Reserve | D42: 3BHK | E42: 12890000 | F42: 1466000 | G42: 45627 | H42: Arjun Mehta | I42: Pune | J42: Walk-in
A43: BK0040 | B43: Geeta Grover | C43: Godrej Horizon | D43: 2BHK | E43: 6510000 | F43: 621000 | G43: 45472 | H43: Sneha Patel | I43: Navi Mumbai | J43: Facebook
A44: BK0041 | B44: Girish Sharma | C44: Godrej Reserve | D44: Penthouse | E44: 30090000 | F44: 2553000 | G44: 45705 | H44: Divya Reddy | I44: Thane | J44: Channel Partner | K44: Elite Property Group
A45: BK0042 | B45: Harish Choudhary | C45: Godrej Summit | D45: 3BHK | E45: 12510000 | F45: 1168000 | G45: 45441 | H45: Sunita Verma | I45: Delhi | J45: Walk-in
A46: BK0043 | B46: Kavita Verma | C46: Godrej Prime | D46: 3BHK+Study | E46: 12760000 | F46: 1207000 | G46: 45635 | H46: Ravi Kumar | I46: Mumbai | J46: Google Ads
A47: BK0044 | B47: Meera Rao | C47: Godrej Azure | D47: Penthouse | E47: 29710000 | F47: 3281000 | G47: 45444 | H47: Ravi Kumar | I47: Pune | J47: Google Ads
A48: BK0045 | B48: Vani Joshi | C48: Godrej Esteem | D48: 2BHK | E48: 7240000 | F48: 740000 | G48: 45613 | H48: Sunita Verma | I48: Hyderabad | J48: Channel Partner | K48: Skyline Properties
A49: BK0046 | B49: Usha Venkatesh | C49: Godrej Prime | D49: 2BHK | E49: 7750000 | F49: 836000 | G49: 45531 | H49: Sneha Patel | I49: Bangalore | J49: Property Portal
A50: BK0047 | B50: Aditya Nair | C50: Godrej Reserve | D50: 3BHK | E50: 12510000 | F50: 1244000 | G50: 45571 | H50: Divya Reddy | I50: Gurgaon | J50: Channel Partner | K50: Skyline Properties
A51: BK0048 | B51: Dinesh Mehta | C51: Godrej Reserve | D51: 3BHK+Study | E51: 13590000 | F51: 1163000 | G51: 45696 | H51: Karan Singh | I51: Chennai | J51: Channel Partner | K51: Urban Nest Advisors
A52: BK0049 | B52: Deepa Das | C52: Godrej Prime | D52: 1BHK | E52: 5500000 | F52: 548000 | G52: 45488 | H52: Sneha Patel | I52: Navi Mumbai | J52: Google Ads
A53: BK0050 | B53: Girish Malhotra | C53: Godrej Reserve | D53: 3BHK | E53: 12080000 | F53: 1208000 | G53: 45745 | H53: Karan Singh | I53: Bangalore | J53: Referral
A54: BK0051 | B54: Pooja Tiwari | C54: Godrej Reserve | D54: 3BHK+Study | E54: 12140000 | F54: 989000 | G54: 45668 | H54: Sneha Patel | I54: Pune | J54: Walk-in
A55: BK0052 | B55: Anita Gupta | C55: Godrej Summit | D55: Penthouse | E55: 34100000 | F55: 2786000 | G55: 45700 | H55: Ravi Kumar | I55: Pune | J55: Website | K55: Prop World Realty
A56: BK0053 | B56: Priya Nair | C56: Godrej Horizon | D56: 1BHK | E56: 6690000 | F56: 658000 | G56: 45750 | H56: Arjun Mehta | I56: Noida | J56: Walk-in
A57: BK0054 | B57: Dinesh Verma | C57: Godrej Esteem | D57: 3BHK | E57: 14000000 | F57: 1203000 | G57: 45667 | H57: Arjun Mehta | I57: Navi Mumbai | J57: Property Portal
A58: BK0055 | B58: Vani Jain | C58: Godrej Meridian | D58: Penthouse | E58: 23210000 | F58: 1891000 | G58: 45520 | H58: Priyanka Sharma | I58: Thane | J58: Website
A59: BK0056 | B59: Priya Krishnan | C59: Godrej Prime | D59: Penthouse | E59: 22320000 | F59: 2206000 | G59: 45519 | H59: Karan Singh | I59: Bangalore | J59: Facebook
A60: BK0057 | B60: Sneha Verma | C60: Godrej Prime | D60: 3BHK | E60: 10600000 | F60: 854000 | G60: 45725 | H60: Pooja Gupta | I60: Ahmedabad | J60: Website
A61: BK0058 | B61: Geeta Verma | C61: Godrej Infinity | D61: 2BHK | E61: 7790000 | F61: 879000 | G61: 45503 | H61: Pooja Gupta | I61: Noida | J61: Facebook
A62: BK0059 | B62: Manoj Mishra | C62: Godrej Azure | D62: 3BHK | E62: 10930000 | F62: 1240000 | G62: 45661 | H62: Priyanka Sharma | I62: Ahmedabad | J62: Channel Partner | K62: Elite Property Group
A63: BK0060 | B63: Meera Krishnan | C63: Godrej Infinity | D63: 1BHK | E63: 4950000 | F63: 419000 | G63: 45694 | H63: Ravi Kumar | I63: Noida | J63: Facebook
A64: BK0061 | B64: Sheela Mehta | C64: Godrej Esteem | D64: 3BHK | E64: 11350000 | F64: 937000 | G64: 45613 | H64: Divya Reddy | I64: Delhi | J64: Walk-in
A65: BK0062 | B65: Anita Rao | C65: Godrej Azure | D65: 4BHK | E65: 22810000 | F65: 2587000 | G65: 45755 | H65: Divya Reddy | I65: Pune | J65: Property Portal
A66: BK0063 | B66: Lakshmi Malhotra | C66: Godrej Reserve | D66: 4BHK | E66: 17010000 | F66: 2025000 | G66: 45565 | H66: Priyanka Sharma | I66: Pune | J66: Google Ads
A67: BK0064 | B67: Divya Arora | C67: Godrej Azure | D67: 3BHK | E67: 12200000 | F67: 1384000 | G67: 45425 | H67: Sunita Verma | I67: Gurgaon | J67: Channel Partner | K67: Heritage Homes
A68: BK0065 | B68: Naveen Kumar | C68: Godrej Infinity | D68: 3BHK+Study | E68: 13450000 | F68: 1257000 | G68: 45542 | H68: Sneha Patel | I68: Ahmedabad | J68: Google Ads
A69: BK0066 | B69: Rohit Banerjee | C69: Godrej Azure | D69: 2BHK | E69: 9680000 | F69: 935000 | G69: 45624 | H69: Sneha Patel | I69: Chennai | J69: Property Portal
A70: BK0067 | B70: Poonam Mehta | C70: Godrej Meridian | D70: 3BHK | E70: 10880000 | F70: 1061000 | G70: 45630 | H70: Sunita Verma | I70: Chennai | J70: Referral
A71: BK0068 | B71: Suresh Jain | C71: Godrej Prime | D71: 1BHK | E71: 4920000 | F71: 549000 | G71: 45480 | H71: Ravi Kumar | I71: Ahmedabad | J71: Referral
A72: BK0069 | B72: Shobha Hegde | C72: Godrej Summit | D72: 3BHK | E72: 10820000 | F72: 872000 | G72: 45655 | H72: Sneha Patel | I72: Ahmedabad | J72: Walk-in
A73: BK0070 | B73: Neha Choudhary | C73: Godrej Reserve | D73: 4BHK | E73: 16060000 | F73: 1400000 | G73: 45531 | H73: Sneha Patel | I73: Noida | J73: Facebook
A74: BK0071 | B74: Sunita Bedi | C74: Godrej Infinity | D74: 3BHK+Study | E74: 14380000 | F74: 1390000 | G74: 45605 | H74: Ravi Kumar | I74: Pune | J74: Google Ads
A75: BK0072 | B75: Rahul Malhotra | C75: Godrej Infinity | D75: 1BHK | E75: 5360000 | F75: 459000 | G75: 45537 | H75: Divya Reddy | I75: Noida | J75: Property Portal
A76: BK0073 | B76: Sunita Mishra | C76: Godrej Meridian | D76: 4BHK | E76: 19460000 | F76: 1743000 | G76: 45456 | H76: Karan Singh | I76: Chennai | J76: Facebook
A77: BK0074 | B77: Suresh Das | C77: Godrej Infinity | D77: 3BHK+Study | E77: 12320000 | F77: 1279000 | G77: 45491 | H77: Pooja Gupta | I77: Gurgaon | J77: Channel Partner | K77: Prop World Realty
A78: BK0075 | B78: Divya Joshi | C78: Godrej Meridian | D78: 3BHK | E78: 10240000 | F78: 1076000 | G78: 45533 | H78: Priyanka Sharma | I78: Mumbai | J78: Referral
A79: BK0076 | B79: Dinesh Venkatesh | C79: Godrej Reserve | D79: 3BHK+Study | E79: 12040000 | F79: 1232000 | G79: 45656 | H79: Rahul Nair | I79: Chennai | J79: Referral
A80: BK0077 | B80: Ravi Srinivasan | C80: Godrej Azure | D80: 3BHK | E80: 13950000 | F80: 1661000 | G80: 45523 | H80: Arjun Mehta | I80: Delhi | J80: Walk-in
A81: BK0078 | B81: Poonam Reddy | C81: Godrej Meridian | D81: 2BHK | E81: 9690000 | F81: 1158000 | G81: 45641 | H81: Divya Reddy | I81: Bangalore | J81: Property Portal
A82: BK0079 | B82: Harish Jain | C82: Godrej Infinity | D82: 2BHK | E82: 9730000 | F82: 1022000 | G82: 45418 | H82: Amit Joshi | I82: Bangalore | J82: Website
A83: BK0080 | B83: Vivek Gupta | C83: Godrej Summit | D83: 3BHK | E83: 11130000 | F83: 941000 | G83: 45688 | H83: Priyanka Sharma | I83: Pune | J83: Referral
A84: BK0081 | B84: Dinesh Das | C84: Godrej Reserve | D84: Penthouse | E84: 29960000 | F84: 2993000 | G84: 45723 | H84: Amit Joshi | I84: Mumbai | J84: Google Ads
A85: BK0082 | B85: Ravi Venkatesh | C85: Godrej Esteem | D85: 4BHK | E85: 16360000 | F85: 1344000 | G85: 45694 | H85: Divya Reddy | I85: Bangalore | J85: Google Ads
A86: BK0083 | B86: Neha Joshi | C86: Godrej Infinity | D86: 4BHK | E86: 19650000 | F86: 1770000 | G86: 45775 | H86: Arjun Mehta | I86: Hyderabad | J86: Property Portal
A87: BK0084 | B87: Sanjay Mehta | C87: Godrej Infinity | D87: 2BHK | E87: 9680000 | F87: 950000 | G87: 45482 | H87: Divya Reddy | I87: Gurgaon | J87: Referral
A88: BK0085 | B88: Naveen Bedi | C88: Godrej Esteem | D88: 3BHK+Study | E88: 16510000 | F88: 1437000 | G88: 45614 | H88: Pooja Gupta | I88: Mumbai | J88: Referral
A89: TOTAL | E89: =SUM(E4:E88) -> 1226640000 | F89: =SUM(F4:F88) -> 119971000

Sheet Payment Tracker
A1: 💰 PAYMENT COLLECTION TRACKER | 85 Accounts | FY 2024-25
A2: Live Balance & Payment Status Tracking | Auto-calculates Outstanding & % Collected
A3: Booking ID | B3: Customer Name | C3: Project | D3: Total Value (₹) | E3: Amount Received (₹) | F3: Balance (₹) | G3: % Collected | H3: Payment Status | I3: Next Due Date
A4: BK0001 | B4: Sunil Srinivasan | C4: Godrej Azure | D4: 30140000 | E4: 25514000 | F4: =D4-E4 -> 4626000 | G4: =IFERROR(E4/D4,0) -> 0.84651626 | H4: On Schedule | I4: 45502
A5: BK0002 | B5: Neha Joshi | C5: Godrej Horizon | D5: 12380000 | E5: 8006000 | F5: =D5-E5 -> 4374000 | G5: =IFERROR(E5/D5,0) -> 0.64668821 | H5: On Schedule | I5: 45769
A6: BK0003 | B6: Deepa Naidu | C6: Godrej Infinity | D6: 35790000 | E6: 27364000 | F6: =D6-E6 -> 8426000 | G6: =IFERROR(E6/D6,0) -> 0.76457111 | H6: On Schedule | I6: 45633
A7: BK0004 | B7: Divya Gupta | C7: Godrej Azure | D7: 8230000 | E7: 5724000 | F7: =D7-E7 -> 2506000 | G7: =IFERROR(E7/D7,0) -> 0.69550425 | H7: On Schedule | I7: 45562
A8: BK0005 | B8: Deepa Sethi | C8: Godrej Prime | D8: 5200000 | E8: 1252000 | F8: =D8-E8 -> 3948000 | G8: =IFERROR(E8/D8,0) -> 0.24076923 | H8: Overdue | I8: 45663
A9: BK0006 | B9: Poonam Patel | C9: Godrej Prime | D9: 5610000 | E9: 1343000 | F9: =D9-E9 -> 4267000 | G9: =IFERROR(E9/D9,0) -> 0.23939394 | H9: Overdue | I9: 45532
A10: BK0007 | B10: Rajesh Jain | C10: Godrej Reserve | D10: 19890000 | E10: 11083000 | F10: =D10-E10 -> 8807000 | G10: =IFERROR(E10/D10,0) -> 0.55721468 | H10: On Schedule | I10: 45563
A11: BK0008 | B11: Girish Choudhary | C11: Godrej Azure | D11: 6730000 | E11: 4908000 | F11: =D11-E11 -> 1822000 | G11: =IFERROR(E11/D11,0) -> 0.72927192 | H11: On Schedule | I11: 45805
A12: BK0009 | B12: Amit Desai | C12: Godrej Meridian | D12: 13480000 | E12: 11495000 | F12: =D12-E12 -> 1985000 | G12: =IFERROR(E12/D12,0) -> 0.85274481 | H12: On Schedule | I12: 45462
A13: BK0010 | B13: Dinesh Iyer | C13: Godrej Azure | D13: 16100000 | E13: 7833000 | F13: =D13-E13 -> 8267000 | G13: =IFERROR(E13/D13,0) -> 0.48652174 | H13: Partial | I13: 45608
A14: BK0011 | B14: Kiran Banerjee | C14: Godrej Horizon | D14: 7820000 | E14: 7170000 | F14: =D14-E14 -> 650000 | G14: =IFERROR(E14/D14,0) -> 0.9168798 | H14: On Schedule | I14: 45690
A15: BK0012 | B15: Sunita Kumar | C15: Godrej Summit | D15: 10320000 | E15: 4803000 | F15: =D15-E15 -> 5517000 | G15: =IFERROR(E15/D15,0) -> 0.46540698 | H15: Partial | I15: 45779
... A88: BK0085 | B88: Naveen Bedi | C88: Godrej Esteem | D88: 16510000 | E88: 9308000 | F88: =D88-E88 -> 7202000 | G88: =IFERROR(E88/D88,0) -> 0.56377953 | H88: On Schedule | I88: 45674
A90: TOTALS | D90: =SUM(D4:D88) -> 1226640000 | E90: =SUM(E4:E88) -> 737846000 | F90: =D90-E90 -> 488794000 | G90: =IFERROR(E90/D90,0) -> 0.60151797

Sheet Site Visit Management
A1: 🏗️ SITE VISIT MANAGEMENT REGISTER | 281 Visits | FY 2024-25
A2: Site Visit Tracking, Feedback Collection & Follow-up Management
A3: Visit ID | B3: Customer Name | C3: Project | D3: Unit Type | E3: Visit Date | F3: Feedback | G3: Follow-up? | H3: Executive
A4: SV0001 | B4: Pooja Patel | C4: Godrej Summit | D4: 2BHK | E4: 45670 | F4: Interested - Needs Discussion | G4: Yes | H4: Priyanka Sharma
A5: SV0002 | B5: Sunil Srinivasan | C5: Godrej Azure | D5: Penthouse | E5: 45435 | F5: Comparing options | G5: No | H5: Sneha Patel
A6: SV0003 | B6: Mohan Srinivasan | C6: Godrej Meridian | D6: 3BHK | E6: 45729 | F6: Needs family visit | G6: Yes | H6: Karan Singh
A7: SV0004 | B7: Arun Desai | C7: Godrej Summit | D7: Penthouse | E7: 45422 | F7: Ready to book | G7: Yes | H7: Sneha Patel
A8: SV0005 | B8: Santosh Choudhary | C8: Godrej Azure | D8: 4BHK | E8: 45724 | F8: Interested - Needs Discussion | G8: Yes | H8: Sunita Verma
A9: SV0006 | B9: Rohit Chopra | C9: Godrej Summit | D9: Penthouse | E9: 45510 | F9: Price concern | G9: Yes | H9: Pooja Gupta
A10: SV0007 | B10: Neha Reddy | C10: Godrej Infinity | D10: Penthouse | E10: 45696 | F10: Price concern | G10: Yes | H10: Priyanka Sharma
A11: SV0008 | B11: Rahul Reddy | C11: Godrej Summit | D11: Penthouse | E11: 45633 | F11: Price concern | G11: Yes | H11: Karan Singh
A12: SV0009 | B12: Usha Mehta | C12: Godrej Reserve | D12: Penthouse | E12: 45478 | F12: Price concern | G12: Yes | H12: Ravi Kumar
A13: SV0010 | B13: Ravi Mukherjee | C13: Godrej Horizon | D13: 3BHK+Study | E13: 45720 | F13: Comparing options | G13: Yes | H13: Arjun Mehta
A14: SV0011 | B14: Sanjay Singh | C14: Godrej Prime | D14: Penthouse | E14: 45660 | F14: Very Interested | G14: Yes | H14: Arjun Mehta
A15: SV0012 | B15: Arun Bhat | C15: Godrej Summit | D15: 4BHK | E15: 45684 | F15: Liked the project | G15: Yes | H15: Arjun Mehta
... A284: SV0281 | B284: Manoj Pillai | C284: Godrej Reserve | D284: 4BHK | E284: 45584 | F284: Liked the project | G284: Yes | H284: Rahul Nair

Sheet Channel Partner Performance
A1: 🤝 CHANNEL PARTNER PERFORMANCE DASHBOARD | Auto-ranked | FY 2024-25
A2: SUMIFS/COUNTIFS Live Calculations | Revenue, Conversions, Partner Tier
A3: Rank | B3: Partner Name | C3: Leads Generated | D3: Site Visits | E3: Bookings | F3: Revenue (₹) | G3: Conversion % | H3: Avg Deal (₹) | I3: Tier
A4: =IFERROR(RANK(F4,F$4:F$11,0),"-") -> 2 | B4: Prop World Realty | C4: =COUNTIFS('Lead Management'!$P$4:$P$503,B4) -> 9 | D4: =COUNTIFS('Lead Management'!$P$4:$P$503,B4,'Lead Management'!$K$4:$K$503,"Site Visit Completed")+COUNTIFS('Lead Management'!$P$4:$P$503,B4,'Lead Management'!$K$4:$K$503,"Booked") -> 5 | E4: =COUNTIFS('Booking Management'!$K$4:$K$200,B4) -> 3 | F4: =SUMIFS('Booking Management'!$E$4:$E$200,'Booking Management'!$K$4:$K$200,B4) -> 59010000 | G4: =IFERROR(E4/C4,0) -> 0.33333333 | H4: =IFERROR(F4/E4,0) -> 19670000 | I4: =IF(G4>=0.25,"🥇 Platinum",IF(G4>=0.15,"🥈 Gold",IF(G4>=0.08,"🥉 Silver","Bronze"))) -> 🥇 Platinum
A5: =IFERROR(RANK(F5,F$4:F$11,0),"-") -> 4 | B5: Urban Nest Advisors | C5: =COUNTIFS('Lead Management'!$P$4:$P$503,B5) -> 6 | D5: =COUNTIFS('Lead Management'!$P$4:$P$503,B5,'Lead Management'!$K$4:$K$503,"Site Visit Completed")+COUNTIFS('Lead Management'!$P$4:$P$503,B5,'Lead Management'!$K$4:$K$503,"Booked") -> 4 | E5: =COUNTIFS('Booking Management'!$K$4:$K$200,B5) -> 2 | F5: =SUMIFS('Booking Management'!$E$4:$E$200,'Booking Management'!$K$4:$K$200,B5) -> 27700000 | G5: =IFERROR(E5/C5,0) -> 0.33333333 | H5: =IFERROR(F5/E5,0) -> 13850000 | I5: =IF(G5>=0.25,"🥇 Platinum",IF(G5>=0.15,"🥈 Gold",IF(G5>=0.08,"🥉 Silver","Bronze"))) -> 🥇 Platinum
A6: =IFERROR(RANK(F6,F$4:F$11,0),"-") -> 6 | B6: Skyline Properties | C6: =COUNTIFS('Lead Management'!$P$4:$P$503,B6) -> 10 | D6: =COUNTIFS('Lead Management'!$P$4:$P$503,B6,'Lead Management'!$K$4:$K$503,"Site Visit Completed")+COUNTIFS('Lead Management'!$P$4:$P$503,B6,'Lead Management'!$K$4:$K$503,"Booked") -> 3 | E6: =COUNTIFS('Booking Management'!$K$4:$K$200,B6) -> 2 | F6: =SUMIFS('Booking Management'!$E$4:$E$200,'Booking Management'!$K$4:$K$200,B6) -> 19750000 | G6: =IFERROR(E6/C6,0) -> 0.2 | H6: =IFERROR(F6/E6,0) -> 9875000 | I6: =IF(G6>=0.25,"🥇 Platinum",IF(G6>=0.15,"🥈 Gold",IF(G6>=0.08,"🥉 Silver","Bronze"))) -> 🥈 Gold
A7: =IFERROR(RANK(F7,F$4:F$11,0),"-") -> 8 | B7: Prime Location Brokers | C7: =COUNTIFS('Lead Management'!$P$4:$P$503,B7) -> 6 | D7: =COUNTIFS('Lead Management'!$P$4:$P$503,B7,'Lead Management'!$K$4:$K$503,"Site Visit Completed")+COUNTIFS('Lead Management'!$P$4:$P$503,B7,'Lead Management'!$K$4:$K$503,"Booked") -> 0 | E7: =COUNTIFS('Booking Management'!$K$4:$K$200,B7) -> 0 | F7: =SUMIFS('Booking Management'!$E$4:$E$200,'Booking Management'!$K$4:$K$200,B7) -> 0 | G7: =IFERROR(E7/C7,0) -> 0 | H7: =IFERROR(F7/E7,0) -> 0 | I7: =IF(G7>=0.25,"🥇 Platinum",IF(G7>=0.15,"🥈 Gold",IF(G7>=0.08,"🥉 Silver","Bronze"))) -> Bronze
A8: =IFERROR(RANK(F8,F$4:F$11,0),"-") -> 3 | B8: Heritage Homes | C8: =COUNTIFS('Lead Management'!$P$4:$P$503,B8) -> 9 | D8: =COUNTIFS('Lead Management'!$P$4:$P$503,B8,'Lead Management'!$K$4:$K$503,"Site Visit Completed")+COUNTIFS('Lead Management'!$P$4:$P$503,B8,'Lead Management'!$K$4:$K$503,"Booked") -> 5 | E8: =COUNTIFS('Booking Management'!$K$4:$K$200,B8) -> 2 | F8: =SUMIFS('Booking Management'!$E$4:$E$200,'Booking Management'!$K$4:$K$200,B8) -> 28300000 | G8: =IFERROR(E8/C8,0) -> 0.22222222 | H8: =IFERROR(F8/E8,0) -> 14150000 | I8: =IF(G8>=0.25,"🥇 Platinum",IF(G8>=0.15,"🥈 Gold",IF(G8>=0.08,"🥉 Silver","Bronze"))) -> 🥈 Gold
A9: =IFERROR(RANK(F9,F$4:F$11,0),"-") -> 5 | B9: Apex Realty Solutions | C9: =COUNTIFS('Lead Management'!$P$4:$P$503,B9) -> 3 | D9: =COUNTIFS('Lead Management'!$P$4:$P$503,B9,'Lead Management'!$K$4:$K$503,"Site Visit Completed")+COUNTIFS('Lead Management'!$P$4:$P$503,B9,'Lead Management'!$K$4:$K$503,"Booked") -> 2 | E9: =COUNTIFS('Booking Management'!$K$4:$K$200,B9) -> 2 | F9: =SUMIFS('Booking Management'!$E$4:$E$200,'Booking Management'!$K$4:$K$200,B9) -> 23300000 | G9: =IFERROR(E9/C9,0) -> 0.66666667 | H9: =IFERROR(F9/E9,0) -> 11650000 | I9: =IF(G9>=0.25,"🥇 Platinum",IF(G9>=0.15,"🥈 Gold",IF(G9>=0.08,"🥉 Silver","Bronze"))) -> 🥇 Platinum
A10: =IFERROR(RANK(F10,F$4:F$11,0),"-") -> 1 | B10: Elite Property Group | C10: =COUNTIFS('Lead Management'!$P$4:$P$503,B10) -> 12 | D10: =COUNTIFS('Lead Management'!$P$4:$P$503,B10,'Lead Management'!$K$4:$K$503,"Site Visit Completed")+COUNTIFS('Lead Management'!$P$4:$P$503,B10,'Lead Management'!$K$4:$K$503,"Booked") -> 5 | E10: =COUNTIFS('Booking Management'!$K$4:$K$200,B10) -> 4 | F10: =SUMIFS('Booking Management'!$E$4:$E$200,'Booking Management'!$K$4:$K$200,B10) -> 73920000 | G10: =IFERROR(E10/C10,0) -> 0.33333333 | H10: =IFERROR(F10/E10,0) -> 18480000 | I10: =IF(G10>=0.25,"🥇 Platinum",IF(G10>=0.15,"🥈 Gold",IF(G10>=0.08,"🥉 Silver","Bronze"))) -> 🥇 Platinum
A11: =IFERROR(RANK(F11,F$4:F$11,0),"-") -> 7 | B11: Metro Housing Services | C11: =COUNTIFS('Lead Management'!$P$4:$P$503,B11) -> 11 | D11: =COUNTIFS('Lead Management'!$P$4:$P$503,B11,'Lead Management'!$K$4:$K$503,"Site Visit Completed")+COUNTIFS('Lead Management'!$P$4:$P$503,B11,'Lead Management'!$K$4:$K$503,"Booked") -> 2 | E11: =COUNTIFS('Booking Management'!$K$4:$K$200,B11) -> 1 | F11: =SUMIFS('Booking Management'!$E$4:$E$200,'Booking Management'!$K$4:$K$200,B11) -> 10320000 | G11: =IFERROR(E11/C11,0) -> 0.090909091 | H11: =IFERROR(F11/E11,0) -> 10320000 | I11: =IF(G11>=0.25,"🥇 Platinum",IF(G11>=0.15,"🥈 Gold",IF(G11>=0.08,"🥉 Silver","Bronze"))) -> 🥉 Silver

Sheet Follow-up Automation
A1: 📅 FOLLOW-UP AUTOMATION | 368 Active Leads | Auto-prioritized by Urgency
A2: Red = Overdue | Orange = Critical Overdue | Yellow = Due Today | Green = Upcoming
A3: Lead ID | B3: Customer Name | C3: Executive | D3: Current Status | E3: Last Call | F3: Next Follow-up | G3: Days Overdue | H3: Priority Action
A4: LD0052 | B4: Vani Reddy | C4: Divya Reddy | D4: New | E4: 45717 | F4: 46183 | G4: =IFERROR(TODAY()-F4,0) -> 18 | H4: =IF(G4>7,"🔴 CRITICAL — Call Immediately",IF(G4>0,"🟠 OVERDUE — Call Today",IF(G4=0,"🟡 DUE TODAY — Schedule Now",IF(G4>-3,"🔵 Due This Week","🟢 Upcoming — On Track")))) -> 🔴 CRITICAL — Call Immediately
A5: LD0096 | B5: Vani Sharma | C5: Rahul Nair | D5: New | E5: 45398 | F5: 46183 | G5: =IFERROR(TODAY()-F5,0) -> 18 | H5: =IF(G5>7,"🔴 CRITICAL — Call Immediately",IF(G5>0,"🟠 OVERDUE — Call Today",IF(G5=0,"🟡 DUE TODAY — Schedule Now",IF(G5>-3,"🔵 Due This Week","🟢 Upcoming — On Track")))) -> 🔴 CRITICAL — Call Immediately
A6: LD0373 | B6: Deepa Jain | C6: Priyanka Sharma | D6: New | E6: 45722 | F6: 46183 | G6: =IFERROR(TODAY()-F6,0) -> 18 | H6: =IF(G6>7,"🔴 CRITICAL — Call Immediately",IF(G6>0,"🟠 OVERDUE — Call Today",IF(G6=0,"🟡 DUE TODAY — Schedule Now",IF(G6>-3,"🔵 Due This Week","🟢 Upcoming — On Track")))) -> 🔴 CRITICAL — Call Immediately
A7: LD0478 | B7: Sneha Choudhary | C7: Karan Singh | D7: New | E7: 45524 | F7: 46183 | G7: =IFERROR(TODAY()-F7,0) -> 18 | H7: =IF(G7>7,"🔴 CRITICAL — Call Immediately",IF(G7>0,"🟠 OVERDUE — Call Today",IF(G7=0,"🟡 DUE TODAY — Schedule Now",IF(G7>-3,"🔵 Due This Week","🟢 Upcoming — On Track")))) -> 🔴 CRITICAL — Call Immediately
A8: LD0068 | B8: Anjali Taneja | C8: Karan Singh | D8: New | E8: 45505 | F8: 46184 | G8: =IFERROR(TODAY()-F8,0) -> 17 | H8: =IF(G8>7,"🔴 CRITICAL — Call Immediately",IF(G8>0,"🟠 OVERDUE — Call Today",IF(G8=0,"🟡 DUE TODAY — Schedule Now",IF(G8>-3,"🔵 Due This Week","🟢 Upcoming — On Track")))) -> 🔴 CRITICAL — Call Immediately
A9: LD0094 | B9: Poonam Mukherjee | C9: Sunita Verma | D9: New | E9: 45496 | F9: 46184 | G9: =IFERROR(TODAY()-F9,0) -> 17 | H9: =IF(G9>7,"🔴 CRITICAL — Call Immediately",IF(G9>0,"🟠 OVERDUE — Call Today",IF(G9=0,"🟡 DUE TODAY — Schedule Now",IF(G9>-3,"🔵 Due This Week","🟢 Upcoming — On Track")))) -> 🔴 CRITICAL — Call Immediately
A10: LD0181 | B10: Anita Singh | C10: Pooja Gupta | D10: New | E10: 45622 | F10: 46184 | G10: =IFERROR(TODAY()-F10,0) -> 17 | H10: =IF(G10>7,"🔴 CRITICAL — Call Immediately",IF(G10>0,"🟠 OVERDUE — Call Today",IF(G10=0,"🟡 DUE TODAY — Schedule Now",IF(G10>-3,"🔵 Due This Week","🟢 Upcoming — On Track")))) -> 🔴 CRITICAL — Call Immediately
A11: LD0185 | B11: Meera Banerjee | C11: Priyanka Sharma | D11: New | E11: 45725 | F11: 46184 | G11: =IFERROR(TODAY()-F11,0) -> 17 | H11: =IF(G11>7,"🔴 CRITICAL — Call Immediately",IF(G11>0,"🟠 OVERDUE — Call Today",IF(G11=0,"🟡 DUE TODAY — Schedule Now",IF(G11>-3,"🔵 Due This Week","🟢 Upcoming — On Track")))) -> 🔴 CRITICAL — Call Immediately
A12: LD0273 | B12: Shobha Shah | C12: Priyanka Sharma | D12: New | E12: 45693 | F12: 46184 | G12: =IFERROR(TODAY()-F12,0) -> 17 | H12: =IF(G12>7,"🔴 CRITICAL — Call Immediately",IF(G12>0,"🟠 OVERDUE — Call Today",IF(G12=0,"🟡 DUE TODAY — Schedule Now",IF(G12>-3,"🔵 Due This Week","🟢 Upcoming — On Track")))) -> 🔴 CRITICAL — Call Immediately
A13: LD0124 | B13: Deepa Verma | C13: Rahul Nair | D13: New | E13: 45439 | F13: 46185 | G13: =IFERROR(TODAY()-F13,0) -> 16 | H13: =IF(G13>7,"🔴 CRITICAL — Call Immediately",IF(G13>0,"🟠 OVERDUE — Call Today",IF(G13=0,"🟡 DUE TODAY — Schedule Now",IF(G13>-3,"🔵 Due This Week","🟢 Upcoming — On Track")))) -> 🔴 CRITICAL — Call Immediately
A14: LD0262 | B14: Geeta Verma | C14: Priyanka Sharma | D14: New | E14: 45543 | F14: 46185 | G14: =IFERROR(TODAY()-F14,0) -> 16 | H14: =IF(G14>7,"🔴 CRITICAL — Call Immediately",IF(G14>0,"🟠 OVERDUE — Call Today",IF(G14=0,"🟡 DUE TODAY — Schedule Now",IF(G14>-3,"🔵 Due This Week","🟢 Upcoming — On Track")))) -> 🔴 CRITICAL — Call Immediately
A15: LD0351 | B15: Santosh Hegde | C15: Ravi Kumar | D15: New | E15: 45700 | F15: 46185 | G15: =IFERROR(TODAY()-F15,0) -> 16 | H15: =IF(G15>7,"🔴 CRITICAL — Call Immediately",IF(G15>0,"🟠 OVERDUE — Call Today",IF(G15=0,"🟡 DUE TODAY — Schedule Now",IF(G15>-3,"🔵 Due This Week","🟢 Upcoming — On Track")))) -> 🔴 CRITICAL — Call Immediately
... A371: LD0119 | B371: Kiran Das | C371: Sunita Verma | D371: New | E371: 45559 | F371: 46215 | G371: =IFERROR(TODAY()-F371,0) -> -14 | H371: =IF(G371>7,"🔴 CRITICAL — Call Immediately",IF(G371>0,"🟠 OVERDUE — Call Today",IF(G371=0,"🟡 DUE TODAY — Schedule Now",IF(G371>-3,"🔵 Due This Week","🟢 Upcoming — On Track")))) -> 🟢 Upcoming — On Track

Sheet Key Insights
A1: 🔍 KEY BUSINESS INSIGHTS — GODREJ PROPERTIES CRM | FY 2024-25
A2: Data-driven findings from 500 leads · 85 bookings · ₹122.66 Cr revenue
A4: 🔴 CRITICAL PROBLEMS — Immediate Action Required
A5: # | B5: Insight | C5: Metric | D5: Current | E5: Target | F5: Gap | G5: Impact | H5: Action
A6: 1 | B6: Overdue Follow-ups | C6: Active leads overdue | D6: 128 leads | E6: 0 leads | F6: 128 leads | G6: ₹18.4 Cr at risk | H6: Call all today
A7: 2 | B7: Oct'24 Revenue Collapse | C7: MoM revenue drop | D7: ₹3.38 Cr | E7: ₹10 Cr | F7: -₹6.62 Cr | G7: Pipeline failure | H7: Review Sep pipeline
A8: 3 | B8: 47 Lost Leads Unanalysed | C8: Loss reason tracking | D8: 0% tracked | E8: 100% | F8: 47 leads | G8: Repeat mistakes | H8: Add loss reason column
A9: 4 | B9: Mar'25 Lead Generation Drop | C9: Monthly leads | D9: 12 leads | E9: 40+ leads | F9: -28 leads | G9: Apr-May revenue at risk | H9: Restart campaigns now
A10: 5 | B10: ₹48.88 Cr Outstanding | C10: Collection rate | D10: 60.2% | E10: 85%+ | F10: ₹48.88 Cr | G10: Cash flow risk | H10: Call 7 overdue accounts
A12: 🟡 SERIOUS GAPS — Fix This Month
A13: # | B13: Insight | C13: Metric | D13: Current | E13: Target | F13: Gap | G13: Impact | H13: Action
A14: 1 | B14: Facebook ROI is poorest | C14: Conv% vs Google Ads | D14: 12.7% | E14: 20%+ | F14: 7.3% gap | G14: Budget waste | H14: Shift budget to Google Ads
A15: 2 | B15: Walk-in leads underperform | C15: Conv% vs avg | D15: 12.6% | E15: 17%+ | F15: 4.4% gap | G15: Missed easy sales | H15: Fix front desk process
A16: 3 | B16: Sunita Verma underperforming | C16: Conversion rate | D16: 9.3% | E16: 17%+ | F16: 7.7% gap | G16: ₹8+ Cr lost | H16: Coaching & review
A17: 4 | B17: Rahul Nair below average | C17: Conversion rate | D17: 11.5% | E17: 17%+ | F17: 5.5% gap | G17: ₹5+ Cr lost | H17: Script training
A18: 5 | B18: Hyderabad worst city | C18: Conversion rate | D18: 8.6% | E18: 17%+ | F18: 8.4% gap | G18: Market issue? | H18: Review project positioning
A20: 🟢 WHAT IS WORKING — Scale These Up
A21: # | B21: Insight | C21: Metric | D21: Current | E21: Benchmark | F21: Advantage | G21: Revenue Impact | H21: Action
A22: 1 | B22: Pune = highest conversion city | C22: Conv rate | D22: 33.3% | E22: 17% avg | F22: +16.3% | G22: ₹27.29 Cr | H22: More inventory + marketing
A23: 2 | B23: Google Ads best ROI source | C23: Conv rate | D23: 23.7% | E23: 17% avg | F23: +6.7% | G23: ₹23.97 Cr | H23: Double the budget
A24: 3 | B24: Divya Reddy = blueprint exec | C24: Conv rate | D24: 28.6% | E24: 17% avg | F24: +11.6% | G24: ₹17.91 Cr | H24: Use her as trainer
A25: 4 | B25: Apex Realty = best partner | C25: Conv rate | D25: 66.7% | E25: 22% avg | F25: +44.7% | G25: ₹2.33 Cr | H25: Give more leads
A26: 5 | B26: 3BHK = volume king | C26: Bookings | D26: 23 bk | E26: 14 avg | F26: +9 bk | G26: ₹26.93 Cr | H26: Prioritise 3BHK inventory
A27: 6 | B27: Penthouse = revenue king | C27: Rev per bk | D27: ₹292L | E27: ₹144L avg | F27: +₹148L/bk | G27: ₹37.94 Cr | H27: Assign top execs only
A28: 7 | B28: Referral top 3 source | C28: Conv rate | D28: 19.5% | E28: 17% avg | F28: +2.5% | G28: ₹22.39 Cr | H28: Build referral program

Sheet Lead Aging Analysis
A1: ⏰ LEAD AGING ANALYSIS | How Long Have Active Leads Been Waiting?
A2: Active pipeline only (Booked & Lost excluded) | Older = Higher Risk of Losing
A4: Fresh (0-7 days) | C4: New (8-15 days) | E4: Growing (16-30 days) | G4: At Risk (31-60 days) | I4: Critical (60+ days)
A5: 0 | C5: 0 | E5: 0 | G5: 0 | I5: 368
A6: 0% of pipeline | C6: 0% of pipeline | E6: 0% of pipeline | G6: 0% of pipeline | I6: 100% of pipeline
A8: Lead ID | B8: Customer Name | C8: Executive | D8: Status | E8: City | F8: Budget (₹) | G8: Lead Date | H8: Age (Days) | I8: Band | J8: Priority
A9: LD0461 | B9: Rajesh Shah | C9: Sunita Verma | D9: Site Visit Completed | E9: Mumbai | F9: 5500000 | G9: 45385 | H9: 816 | I9: Critical | J9: 🔴 URGENT
A10: LD0494 | B10: Mohan Malhotra | C10: Rahul Nair | D10: Site Visit Scheduled | E10: Noida | F10: 13500000 | G10: 45386 | H10: 815 | I10: Critical | J10: 🔴 URGENT
A11: LD0240 | B11: Rahul Verma | C11: Ravi Kumar | D11: Negotiation | E11: Gurgaon | F11: 9000000 | G11: 45387 | H11: 814 | I11: Critical | J11: 🔴 URGENT
A12: LD0406 | B12: Sunita Pandey | C12: Karan Singh | D12: Site Visit Scheduled | E12: Mumbai | F12: 17100000 | G12: 45387 | H12: 814 | I12: Critical | J12: 🔴 URGENT
A13: LD0318 | B13: Sneha Rao | C13: Divya Reddy | D13: Follow-up | E13: Mumbai | F13: 9400000 | G13: 45389 | H13: 812 | I13: Critical | J13: 🔴 URGENT
A14: LD0423 | B14: Harish Kapoor | C14: Pooja Gupta | D14: Negotiation | E14: Kolkata | F14: 5300000 | G14: 45389 | H14: 812 | I14: Critical | J14: 🔴 URGENT
A15: LD0192 | B15: Kiran Sethi | C15: Divya Reddy | D15: Follow-up | E15: Thane | F15: 12900000 | G15: 45390 | H15: 811 | I15: Critical | J15: 🔴 URGENT
A16: LD0383 | B16: Arun Joshi | C16: Pooja Gupta | D16: Follow-up | E16: Chennai | F16: 12800000 | G16: 45390 | H16: 811 | I16: Critical | J16: 🔴 URGENT
A17: LD0199 | B17: Sunil Jain | C17: Ravi Kumar | D17: Site Visit Scheduled | E17: Navi Mumbai | F17: 4500000 | G17: 45391 | H17: 810 | I17: Critical | J17: 🔴 URGENT
A18: LD0441 | B18: Sanjay Bedi | C18: Rahul Nair | D18: Negotiation | E18: Ahmedabad | F18: 20100000 | G18: 45392 | H18: 809 | I18: Critical | J18: 🔴 URGENT
A19: LD0096 | B19: Vani Sharma | C19: Rahul Nair | D19: New | E19: Chennai | F19: 8800000 | G19: 45396 | H19: 805 | I19: Critical | J19: 🔴 URGENT
A20: LD0016 | B20: Dinesh Agarwal | C20: Arjun Mehta | D20: Follow-up | E20: Kolkata | F20: 4600000 | G20: 45399 | H20: 802 | I20: Critical | J20: 🔴 URGENT
... A108: LD0094 | B108: Poonam Mukherjee | C108: Sunita Verma | D108: New | E108: Mumbai | F108: 11100000 | G108: 45491 | H108: 710 | I108: Critical | J108: 🔴 URGENT

Sheet Target vs Achievement
A1: 🎯 EXECUTIVE TARGET vs ACHIEVEMENT TRACKER | FY 2024-25
A2: Revenue Targets vs Actual · Booking Targets vs Actual · Performance Rating
A4: SECTION A: MONTHLY REVENUE TARGET vs ACTUAL
A5: Month | B5: Target (₹) | C5: Actual (₹) | D5: Variance (₹) | E5: Achievement % | F5: Bookings | G5: Booking Target | H5: Status | I5: MoM Change | J5: Recommendation
A6: Apr'24 | B6: 8000000 | C6: 4920000 | D6: -3080000 | E6: 0.615 | F6: 6 | G6: 8 | H6: ❌ Missed | J6: Review pipeline
A7: May'24 | B7: 8000000 | C7: 7670000 | D7: -330000 | E7: 0.95875 | F7: 9 | G7: 8 | H7: ⚠️ Near | I7: 0.55894309 | J7: Push harder
A8: Jun'24 | B8: 10000000 | C8: 12290000 | D8: 2290000 | E8: 1.229 | F8: 8 | G8: 8 | H8: ✅ Hit | I8: 0.60234681 | J8: Scale up
A9: Jul'24 | B9: 10000000 | C9: 8120000 | D9: -1880000 | E9: 0.812 | F9: 9 | G9: 8 | H9: ⚠️ Near | I9: -0.33930024 | J9: Push harder
A10: Aug'24 | B10: 10000000 | C10: 17730000 | D10: 7730000 | E10: 1.773 | F10: 8 | G10: 8 | H10: ✅ Hit | I10: 1.1834975 | J10: Scale up
A11: Sep'24 | B11: 10000000 | C11: 10350000 | D11: 350000 | E11: 1.035 | F11: 3 | G11: 8 | H11: ✅ Hit | I11: -0.41624365 | J11: Scale up
A12: Oct'24 | B12: 12000000 | C12: 3380000 | D12: -8620000 | E12: 0.28166667 | F12: 7 | G12: 8 | H12: ❌ Missed | I12: -0.67342995 | J12: Review pipeline
A13: Nov'24 | B13: 12000000 | C13: 7020000 | D13: -4980000 | E13: 0.585 | F13: 10 | G13: 8 | H13: ❌ Missed | I13: 1.0769231 | J13: Review pipeline
A14: Dec'24 | B14: 12000000 | C14: 8660000 | D14: -3340000 | E14: 0.72166667 | F14: 7 | G14: 8 | H14: ❌ Missed | I14: 0.23361823 | J14: Review pipeline
A15: Jan'25 | B15: 12000000 | C15: 14970000 | D15: 2970000 | E15: 1.2475 | F15: 9 | G15: 8 | H15: ✅ Hit | I15: 0.72863741 | J15: Scale up
A16: Feb'25 | B16: 12000000 | C16: 13610000 | D16: 1610000 | E16: 1.1341667 | F16: 7 | G16: 8 | H16: ✅ Hit | I16: -0.090848363 | J16: Scale up
A17: Mar'25 | B17: 15000000 | C17: 13930000 | D17: -1070000 | E17: 0.92866667 | F17: 2 | G17: 8 | H17: ⚠️ Near | I17: 0.023512123 | J17: Push harder
A18: FULL YEAR TOTAL | B18: 131000000 | C18: 122650000 | D18: -8350000 | E18: 0.93625954 | F18: 85 | G18: 96
A20: SECTION B: EXECUTIVE TARGET vs ACHIEVEMENT
A21: Executive | B21: Revenue Target | C21: Revenue Actual | D21: Gap (₹) | E21: Achievement % | F21: Booking Target | G21: Bookings Actual | H21: Conversion % | I21: Score | J21: Rating
A22: Divya Reddy | B22: 18000000 | C22: 17910000 | D22: 90000 | E22: 0.995 | F22: 12 | G22: 14 | H22: 0.286 | I22: 103.4 | J22: ⭐ Star
A23: Sneha Patel | B23: 20000000 | C23: 18880000 | D23: 1120000 | E23: 0.944 | F23: 14 | G23: 14 | H23: 0.246 | I23: 92.4 | J23: ⭐ Star
A24: Priyanka Sharma | B24: 18000000 | C24: 18170000 | D24: -170000 | E24: 1.0094444 | F24: 12 | G24: 11 | H24: 0.229 | I24: 90.8 | J24: ⭐ Star
A25: Karan Singh | B25: 20000000 | C25: 17490000 | D25: 2510000 | E25: 0.8745 | F25: 14 | G25: 12 | H25: 0.197 | I25: 80.4 | J25: ✅ Good
A26: Ravi Kumar | B26: 15000000 | C26: 13260000 | D26: 1740000 | E26: 0.884 | F26: 10 | G26: 7 | H26: 0.127 | I26: 69.1 | J26: ⚠️ Average
A27: Arjun Mehta | B27: 12000000 | C27: 8600000 | D27: 3400000 | E27: 0.71666667 | F27: 8 | G27: 6 | H27: 0.154 | I27: 66.6 | J27: ⚠️ Average
A28: Amit Joshi | B28: 12000000 | C28: 8900000 | D28: 3100000 | E28: 0.74166667 | F28: 8 | G28: 4 | H28: 0.103 | I28: 55 | J28: ❌ Below
A29: Pooja Gupta | B29: 12000000 | C29: 8130000 | D29: 3870000 | E29: 0.6775 | F29: 8 | G29: 7 | H29: 0.123 | I29: 65.7 | J29: ⚠️ Average
A30: Rahul Nair | B30: 12000000 | C30: 7050000 | D30: 4950000 | E30: 0.5875 | F30: 8 | G30: 6 | H30: 0.115 | I30: 57.5 | J30: ❌ Below
A31: Sunita Verma | B31: 10000000 | C31: 4280000 | D31: 5720000 | E31: 0.428 | F31: 7 | G31: 4 | H31: 0.093 | I31: 43.6 | J31: ❌ Below

Sheet Source ROI Analysis
A1: 📡 LEAD SOURCE ROI ANALYSIS | Where to Invest Your Marketing Budget
A2: Conversion Rate · Revenue per Lead · Cost Efficiency · Strategic Recommendation
A4: Rank | B4: Source | C4: Leads | D4: Bookings | E4: Conv % | F4: Revenue (₹) | G4: Rev per Lead (₹) | H4: Avg Deal (₹) | I4: ROI Score | J4: Recommendation
A5: 1 | B5: Google Ads | C5: 59 | D5: 14 | E5: 0.237 | F5: 23970000 | G5: 406271.19 | H5: 1712142.9 | I5: 47.1 | J5: 🚀 Scale Up
A6: 2 | B6: Channel Partner | C6: 66 | D6: 15 | E6: 0.227 | F6: 20810000 | G6: 315303.03 | H6: 1387333.3 | I6: 39.5 | J6: 🚀 Scale Up
A7: 3 | B7: Referral | C7: 87 | D7: 17 | E7: 0.195 | F7: 22390000 | G7: 257356.32 | H7: 1317058.8 | I7: 33 | J7: ✅ Maintain
A8: 4 | B8: Property Portal | C8: 64 | D8: 10 | E8: 0.156 | F8: 16710000 | G8: 261093.75 | H8: 1671000 | I8: 30.5 | J8: ✅ Maintain
A9: 5 | B9: Website | C9: 66 | D9: 9 | E9: 0.136 | F9: 16640000 | G9: 252121.21 | H9: 1848888.9 | I9: 28.4 | J9: ⚙️ Optimise
A10: 6 | B10: Walk-in | C10: 95 | D10: 12 | E10: 0.126 | F10: 13260000 | G10: 139578.95 | H10: 1105000 | I10: 19.3 | J10: ⚙️ Optimise
A11: 7 | B11: Facebook | C11: 63 | D11: 8 | E11: 0.127 | F11: 8860000 | G11: 140634.92 | H11: 1107500 | I11: 19.4 | J11: ⚙️ Optimise
A13: 💡 KEY INSIGHT: Google Ads converts 23.7% vs Facebook 12.7% — shift budget from Facebook to Google Ads → projected +40 bookings → +₹5.8 Cr additional revenue

Sheet Revenue Forecast
A1: 📈 REVENUE FORECAST | Next 6 Months | Based on Pipeline Analysis
A2: Conservative · Base · Optimistic scenarios based on current pipeline & conversion rates
A4: Month | B4: Active Leads | C4: Expected SV | D4: Conservative (₹) | E4: Base Case (₹) | F4: Optimistic (₹) | G4: Target (₹) | H4: Key Assumption
A5: Apr'25 | B5: 368 | C5: 85 | D5: 8000000 | E5: 10500000 | F5: 14000000 | G5: 12000000 | H5: 28 overdue leads converting
A6: May'25 | B6: 340 | C6: 90 | D6: 9000000 | E6: 12000000 | F6: 16000000 | G6: 12000000 | H6: New lead gen ramp-up
A7: Jun'25 | B7: 380 | C7: 95 | D7: 10000000 | E7: 13500000 | F7: 18000000 | G7: 12000000 | H7: Q1 FY26 campaign launch
A8: Jul'25 | B8: 400 | C8: 100 | D8: 11000000 | E8: 14000000 | F8: 19000000 | G8: 15000000 | H8: Channel partner expansion
A9: Aug'25 | B9: 420 | C9: 110 | D9: 12000000 | E9: 15500000 | F9: 21000000 | G9: 15000000 | H9: Peak booking season
A10: Sep'25 | B10: 440 | C10: 115 | D10: 11000000 | E10: 14500000 | F10: 20000000 | G10: 15000000 | H10: Year-end push
A11: 6-MONTH TOTAL | D11: 61000000 | E11: 80000000 | F11: 108000000 | G11: 81000000
A13: SCENARIO ANALYSIS — What Would Drive Each Outcome
A14: 🔴 Conservative | C14: ₹61 Cr | D14: Current conversion rate maintained, no improvement in follow-ups or lead gen
A15: 🔵 Base Case | C15: ₹80 Cr | D15: Fix overdue follow-ups, maintain Google Ads budget, coach 2 underperforming execs
A16: 🟢 Optimistic | C16: ₹108 Cr | D16: Scale Google Ads, expand Pune market, activate Apex Realty, Divya trains team

Sheet Pivot Data
A1: 📊 PIVOT & SUMMARY DATA — Dashboard Source Tables
A3: MONTHLY PERFORMANCE | G3: LEAD SOURCE ANALYSIS | L3: PROJECT REVENUE
A4: Month | B4: Leads | C4: Site Visits | D4: Bookings | E4: Revenue (₹) | G4: Source | H4: Leads | I4: Bookings | J4: Conv% | L4: Project | M4: Bookings | N4: Revenue (₹)
A5: Apr 24 | B5: 34 | C5: 16 | D5: 6 | E5: 49150000 | G5: Facebook | H5: 63 | I5: 8 | J5: 12.7% | L5: Godrej Azure | M5: 11 | N5: 196640000
A6: May 24 | B6: 47 | C6: 30 | D6: 9 | E6: 76710000 | G6: Website | H6: 66 | I6: 9 | J6: 13.6% | L6: Godrej Horizon | M6: 12 | N6: 138440000
A7: Jun 24 | B7: 46 | C7: 30 | D7: 8 | E7: 122950000 | G7: Google Ads | H7: 59 | I7: 14 | J7: 23.7% | L7: Godrej Infinity | M7: 11 | N7: 158120000
A8: Jul 24 | B8: 39 | C8: 21 | D8: 9 | E8: 81210000 | G8: Referral | H8: 87 | I8: 17 | J8: 19.5% | L8: Godrej Prime | M8: 14 | N8: 146380000
A9: Aug 24 | B9: 39 | C9: 26 | D9: 8 | E9: 177450000 | G9: Channel Partner | H9: 66 | I9: 15 | J9: 22.7% | L9: Godrej Reserve | M9: 14 | N9: 247810000
A10: Sep 24 | B10: 40 | C10: 17 | D10: 3 | E10: 103410000 | G10: Walk-in | H10: 95 | I10: 12 | J10: 12.6% | L10: Godrej Meridian | M10: 9 | N10: 128350000
A11: Oct 24 | B11: 48 | C11: 26 | D11: 7 | E11: 33810000 | G11: Property Portal | H11: 64 | I11: 10 | J11: 15.6% | L11: Godrej Summit | M11: 6 | N11: 89880000
A12: Nov 24 | B12: 52 | C12: 23 | D12: 10 | E12: 70270000 | L12: Godrej Esteem | M12: 8 | N12: 121020000
A13: Dec 24 | B13: 43 | C13: 23 | D13: 7 | E13: 86560000
A14: Jan 25 | B14: 56 | C14: 38 | D14: 9 | E14: 149770000
A15: Feb 25 | B15: 44 | C15: 25 | D15: 7 | E15: 136090000
A16: Mar 25 | B16: 12 | C16: 6 | D16: 2 | E16: 139260000
A19: SALES FUNNEL | G19: EXECUTIVE SUMMARY
A20: Stage | B20: Count | C20: % of Total | G20: Executive | H20: Bookings | I20: Revenue (₹)
A21: New | B21: 74 | C21: 14.8% | G21: Sneha Patel | H21: 14 | I21: 188760000
A22: Follow-up | B22: 98 | C22: 19.6% | G22: Divya Reddy | H22: 14 | I22: 179070000
A23: Site Visit Scheduled | B23: 61 | C23: 12.2% | G23: Amit Joshi | H23: 4 | I23: 88960000
A24: Site Visit Completed | B24: 70 | C24: 14.0% | G24: Karan Singh | H24: 12 | I24: 174890000
A25: Negotiation | B25: 65 | C25: 13.0% | G25: Rahul Nair | H25: 6 | I25: 70510000
A26: Booked | B26: 85 | C26: 17.0% | G26: Priyanka Sharma | H26: 11 | I26: 181730000
A27: Lost | B27: 47 | C27: 9.4% | G27: Arjun Mehta | H27: 6 | I27: 85990000
A28: ⚠ Dashboard KPI tiles show values at generation date. Refresh from Pivot Data for live updates. | G28: Ravi Kumar | H28: 7 | I28: 132620000
G29: Pooja Gupta | H29: 7 | I29: 81280000
G30: Sunita Verma | H30: 4 | I30: 42830000
